Workbook
Name Development_fee: [1]Инвестиции!$D$28
Name Непредвиденные: [1]Инвестиции!$D$35
Name Технический_заказчик: [1]Инвестиции!$D$30
Name Управление_базовое: [1]Инвестиции!$D$34

Sheet ТЭПы
B2: Название проекта | C2: Дербеневская набережная по калькулятору Саевой
A3: Условия
B4: Ценовая концепция | C4: БИЗНЕС
B5: Срок реализации проекта / мес | C5: 7.25 | D5: почему 4? В годах или месяцах?
B6: срок покупки ЗУ | C6: 3 кв 2025-4 кв 2025
B7: срок получения РНС | C7: 4 кв 2025
B8: Старт продаж | C8: 1 кв 2026
B9: Завершение СМР без отделки | C9: 1 кв 2032
B10: Ввод в эксплуатацию (это получение РнС?) | C10: 30.09.2029; 01.03.2031; 01.07.2031; 01.10.2031
B11: Завершение продаж | C11: 4 кв 2033
B12: Срок окончания ПФ | C12: 2 кв 2032
B13: Кадастровая стоимость ЗУ | C13: 5834907660 | D13: какая? После смены ВРИ? Или до? Как рассчитывать астоимость аренды? | I13: 5834907660
A14: ТЭПы
B15: Площадь ЗУ / м2 | C15: 96572 | I15: 96572
B16: Корпусность | H16: как аренду считать?
B17: Количество очередей | C17: 3
B18: Этажность
B19: Площадь проекта - СПП (ГНС) | C19: 221967 | E19: только наземная часть?
B20: Площадь жилой застройки | C20: =210038+420 -> 210458 | D20: =C20/C19 -> 0.94814995 | E20: только наземная часть? ГВС?
B21: Площадь нежилой застройки | C21: 19009 | D21: =C21/C19 -> 0.085638856 | E21: почему 8%? Всегда так или это какое то среднее значение?
B22: Площадь Квартир (продаваемая?) | C22: 143560 | D22: =C22/C20 -> 0.68213135
B23: Площадь коммерции продаваемая | C23: =10322 -> 10322 | D23: 0.8
B24: Лобби (не входит в продаваемую?) | E24: что это? Как рассчитывается?
B25: Клубная инфраструктура | E25: что это? Как рассчитывается?
B26: МОП под отделку+ ресепшн | C26: =51775+7719 -> 59494 | D26: =C26/C19 -> 0.26803083
B27: Количество парковочных мест ЖК | C27: 862 | D27: =I44 -> 1.2 | E27: средний
B28: Кол-во квартир | C28: 2401 | D28: =C28/C27 -> 2.7853828 | E28: обеспеченность | F28: это входит в норму?
B29: Площадь благоустройства | C29: =C15*D29 -> 28971.6 | D29: 0.3 | E29: уточнить это доп благоустройство? в СМР не входит?
B30: Внутриквартальный проезд | C30: =$C$29*D30 -> 2897.16 | D30: 0.1 | E30: откуда нормативы?
B31: Озеленение | C31: =$C$29*D31 -> 2897.16 | D31: 0.1 | E31: откуда нормативы?
B32: Зона наземной парковки | C32: =$C$29*D32 -> 2897.16 | D32: =D29-D30-D31 -> 0.1 | E32: откуда нормативы?
B33: Площадь застройки | C33: =C15-C29 -> 67600.4 | D33: =C33/C15 -> 0.7
B34: Площадь подземной парковки | C34: =E49 -> 35294.59
B35: Продаваемая площадь | C35: 149281
B38: Квартирография - цены старта продаж | E38: =E44+E51 -> 189176.98 | F38: =F44+F51 -> 3392.025
B40: Типы квартир | D40: S квартиры | E40: S | F40: кол-во | G40: цена 1м2 | H40: Средний чек | I40: Норматив | J40: Машиноместа
B41: Квартиры Тип 1 | C41: 0.4 | D41: 35.108 | E41: =D41*F41 -> 33738.788 | F41: 961 | G41: 497703 | H41: =G41*D41 -> 17473357 | I41: 0.8 | J41: =I41*F41 -> 768.8
B42: Квартиры Тип 2 | C42: 0.3 | D42: 60.53 | E42: =F42*D42 -> 43581.6 | F42: 720 | G42: 497703 | H42: =G42*D42 -> 30125963 | I42: 1.2 | J42: =I42*F42 -> 864
B43: Квартиры Тип 3 | C43: 0.3 | D43: 92 | E43: =F43*D43 -> 66240 | F43: 720 | G43: 497703 | H43: =G43*D43 -> 45788676 | I43: 1.6 | J43: =I43*F43 -> 1152
D44: =E44/F44 -> 59.791915 | E44: =SUM(E41:E43) -> 143560.39 | F44: 2401 | G44: =AVERAGE(G41:G43) -> 497703 | H44: =AVERAGE(H41:H43) -> 31129332 | I44: =AVERAGE(I41:I43) -> 1.2 | J44: 862 | K44: как в ФМ
B47: Типы прочих помещений | D47: S коммерции | E47: S | F47: кол-во | G47: цена 1м2 | H47: Средний чек
B48: ПСН | C48: 10332 | D48: 80 | E48: =C23 -> 10322 | F48: =E48/D48 -> 129.025 | G48: 600000 | H48: =G48*D48 -> 48000000
B49: Машиноместа | C49: 5200 | D49: 40.945 | E49: =D49*F49 -> 35294.59 | F49: =J44 -> 862 | G49: 270000 | H49: =G49*D49 -> 11055150
B50: Прочие помещения | D50: 0 | E50: 0 | F50: 0 | H50: =G50*D50 -> 0
E51: =SUM(E48:E50) -> 45616.59 | F51: =SUM(F48:F50) -> 991.025 | G51: =AVERAGE(G48:G50) -> 435000
A54: Основные оказатели

Sheet Бюджет 
A3: Доходы | D3: Цена Средняя | E3: Площадь | F3: Выручка | G3: Средий чек
C5: ='План продаж'!C27 -> Квартиры Тип 1 | D5: ='План продаж'!D31 -> 573799.03 | E5: ='План продаж'!D29 -> 33738.788 | F5: ='План продаж'!D27 -> 2.2164067e+10 | G5: ='План продаж'!I8 -> 17473357
C6: ='План продаж'!C32 -> Квартиры Тип 2 | D6: ='План продаж'!D36 -> 573799.03 | E6: ='План продаж'!D34 -> 36620.65 | F6: ='План продаж'!D32 -> 2.8633526e+10 | G6: ='План продаж'!I9 -> 30125963
C7: ='План продаж'!C37 -> Квартиры Тип 3 | D7: ='План продаж'!D41 -> 573799.03 | E7: ='План продаж'!D39 -> 35604 | F7: ='План продаж'!D37 -> 4.3534979e+10 | G7: ='План продаж'!I10 -> 45788676
C8: ='План продаж'!C42 -> ПСН | D8: ='План продаж'!D46 -> 691736.68 | E8: ='План продаж'!D44 -> 10888.608 | F8: ='План продаж'!D42 -> 1.0206468e+10 | G8: ='План продаж'!I15 -> 48000000
C9: ='План продаж'!C47 -> Машиноместа | D9: ='План продаж'!I16 -> 11055150 | E9: ='План продаж'!D48 -> 862 | F9: ='План продаж'!D47 -> 1.3591248e+10 | G9: ='План продаж'!I16 -> 11055150
C10: ='План продаж'!C52 -> Прочие помещения | D10: ='План продаж'!D56 -> 0 | E10: ='План продаж'!D54 -> 0 | F10: ='План продаж'!D52 -> 0 | G10: ='План продаж'!I17 -> 0
C12: ИТОГО | F12: =SUM(F5:F11) -> 1.1813029e+11
A15: Расходы | D15: Расценка | E15: Объем
B16: Правообладание | F16: =SUM(F17:F19) -> 1330355898 | G16: =F16/$F$59 -> 0.013300587
C17: ='CF1 '!A21 -> Покупка и формирование актива, агентские , diudill | D17: =F17/E17 -> 13775.793 | E17: =ТЭПы!C15 -> 96572 | F17: =2440190898-F22 -> 1330355898 | G17: =F17/$F$59 -> 0.013300587
C18: Юридические расходы на покупку | D18: =F18/E18 -> 0 | E18: =ТЭПы!C15 -> 96572 | F18: 0 | G18: =F18/$F$59 -> 0
C19: Агентское вознаграждение | D19: 0.02 | E19: =F17 -> 1330355898 | F19: 0 | G19: =F19/$F$59 -> 0
B20: ='CF1 '!A23 -> Земельно-имущественные отношения | F20: =SUM(F21:F22) -> 1.9349595e+09 | G20: =F20/$F$59 -> 0.019345273
C21: ='CF1 '!A24 -> Аренда/налог ЗУ | D21: =F21/E21 -> 8544.1383 | E21: =ТЭПы!C15 -> 96572 | F21: 8.2512453e+08 | G21: =F21/$F$59 -> 0.008249402
C22: ='CF1 '!A25 -> Плата за изменение ВРИ | D22: 5000 | E22: =ТЭПы!C19 -> 221967 | F22: =E22*D22 -> 1109835000 | G22: =F22/$F$59 -> 0.011095871 | H22: от площади ГНС
B23: ПиР | F23: =SUM(F24:F29) -> 2.0131747e+09 | G23: =F23/$F$59 -> 0.020127249
C24: ='CF1 '!A28 -> Компенсация городу | D24: =F24/E24 -> 8440.6856 | E24: =ТЭПы!C35 -> 149281 | F24: 1.260034e+09 | G24: =F24/$F$59 -> 0.012597525 | H24: уточнить у Елены расценку, перенести в раздел "правообладание" Это не ПИР
C25: ='CF1 '!A30 -> Получение ИРД (ППТ,ГПЗУ) | F25: =D25*E25 -> 0 | G25: =F25/$F$59 -> 0
C26: ='CF1 '!A32 -> Проектирование объектов стадия П | D26: =F26/E26 -> 5031.7232 | E26: =ТЭПы!C35 -> 149281 | F26: 751140673 | G26: =F26/$F$59 -> 0.0075097288 | H26: уточнить у Елены расценку
C27: ='CF1 '!A34 -> Проектирование объектов стадия РД | F27: =D27*E27 -> 0 | G27: =F27/$F$59 -> 0
C28: ='CF1 '!A36 -> Инженерные изыскания (опер деятельность) | F28: =D28*E28 -> 0 | G28: =F28/$F$59 -> 0
C29: ='CF1 '!A38 -> Предпроектные проработки | D29: 2000000 | E29: 1 | F29: =D29*E29 -> 2000000 | G29: =F29/$F$59 -> 1.9995532e-05 | H29: уточнить у Елены расценку
B30: СМР | F30: =SUM(F31:F49) -> 6.5294814e+10 | G30: =F30/$F$59 -> 0.65280228
C31: ='CF1 '!A41 -> Подготовка площадки (включая снос) | D31: =F31/E31 -> 1465.7932 | E31: =ТЭПы!C15 -> 96572 | F31: 141554585 | G31: =F31/$F$59 -> 0.0014152296 | H31: какая единица изм? Уточнить как брать расценку и обем?
C32: ='CF1 '!A43 -> СМР надземной части (в т.ч. стилобат) | D32: =F32/E32 -> 353578.93 | E32: =ТЭПы!C35 -> 149281 | F32: 52782616084 | G32: =F32/$F$59 -> 0.52770825 | H32: объем изменила на продаваемую площадь (кв+ком)
C33: ='CF1 '!A45 -> СМР подземной части | D33: =400000*0.22 -> 88000 | E33: 0 | F33: =E33*D33 -> 0 | G33: =F33/$F$59 -> 0
C34: ='CF1 '!A47 -> Отделка МОП | D34: =400000*0.12 -> 48000 | E34: 0 | F34: =E34*D34 -> 0 | G34: =F34/$F$59 -> 0
C35: ='CF1 '!A49 -> ТУ и плата за тех. присоединение | D35: =F35/E35 -> 7687.9557 | E35: =ТЭПы!C35 -> 149281 | F35: =2295331433.88/2 -> 1.1476657e+09 | G35: =F35/$F$59 -> 0.011474093 | H35: что обозначает объем (цифра 5 )?
C36: ='CF1 '!A51 -> Наружные сети и сооружения | D36: =F36/E36 -> 7687.9557 | E36: =ТЭПы!C35 -> 149281 | F36: =F35 -> 1.1476657e+09 | G36: =F36/$F$59 -> 0.011474093 | H36: что обозначает объем (цифра 5 )?
C37: ='CF1 '!A53 -> Благоустройство, объекты транспортного хозяйства | D37: =F37/E37 -> 46.802386 | E37: =ТЭПы!C29 -> 28971.6 | F37: 1355940 | G37: =F37/$F$59 -> 1.3556371e-05
C38: Устройство УДС | D38: =F38/E38 -> 3588.0042 | E38: =ТЭПы!C35 -> 149281 | F38: 535620851
C39: ='CF1 '!A55 -> Прочие СМР | D39: =F39/E39 -> 113.24249 | E39: =ТЭПы!C35 -> 149281 | F39: 16904953 | G39: =F39/$F$59 -> 0.00016901176 | H39: сопутствующи
C40: ='CF1 '!A57 -> Иные расходы на проекты (охрана, содержание площадки) | D40: =F40/E40 -> 380.74206 | E40: =ТЭПы!C35 -> 149281 | F40: 56837556 | G40: =F40/$F$59 -> 0.00056824859
C41: ='CF1 '!A59 -> Расходы по вводу в эксплуатацию | D41: 1000 | E41: =ТЭПы!C35 -> 149281 | F41: 0 | G41: =F41/$F$59 -> 0 | H41: объем изменила на продаваемую площадь (кв+ком)
C42: ='CF1 '!A61 -> Непредвиденные расходы | D42: =(D32+D33+D34)*10% -> 48957.893 | E42: =ТЭПы!C22+ТЭПы!C23 -> 153882 | F42: =E42+D42 -> 202839.89 | G42: =F42/$F$59 -> 2.0279458e-06
C43: ='CF1 '!A63 -> Услуги технического заказчика | D43: =F43/E43 -> 0.020173823 | E43: ='План продаж'!D25 -> 1.1813029e+11 | F43: 2383139493 | G43: =F43/$F$59 -> 0.023826071
C44: ='CF1 '!A65 -> Авторский надзор | F44: =E44*D44 -> 0 | G44: =F44/$F$59 -> 0
C45: ='CF1 '!A67 -> Мониторинг окружающей застройки | F45: 88670039 | G45: =F45/$F$59 -> 0.00088650231 | H45: операц расходы из ФМ
C46: Тех Надзор | F46: =E46*D46 -> 0 | G46: =F46/$F$59 -> 0
C47: ='CF1 '!A71 -> Социальные объекты (отдельно возводимые) | D47: =F47/E47 -> 34351.794 | E47: =ТЭПы!C35 -> 149281 | F47: 5.1280701e+09 | G47: =F47/$F$59 -> 0.051269246
C48: ='CF1 '!A73 -> Вознаграждение за управление проектом | D48: 0.02 | E48: ='План продаж'!D25 -> 1.1813029e+11 | F48: 1850054797 | G48: =F48/$F$59 -> 0.018496415
C49: ='CF1 '!A75 -> Содержание застройщика | D49: =F49/E49 -> 0.00012236363 | E49: ='План продаж'!D25 -> 1.1813029e+11 | F49: 14454851 | G49: =F49/$F$59 -> 0.00014451622
B50: Коммерческие расходы | F50: =SUM(F51:F52) -> 8.3293693e+09 | G50: =F50/$F$59 -> 0.083275086
C51: Маркетинг | D51: 0.035 | E51: =F12 -> 1.1813029e+11 | F51: =8389618415.5/2 -> 4.1948092e+09 | G51: =F51/$F$59 -> 0.041938721
C52: Продажи | D52: 0.035 | E52: =F12 -> 1.1813029e+11 | F52: =E52*D52 -> 4.1345601e+09 | G52: =F52/$F$59 -> 0.041336365
B53: Налоги | F53: =SUM(F54:F55) -> 6.7334264e+09
C54: НДС | D54: 0.22 | E54: =(F30+F23+F16)-'План продаж'!D60 -> 4.4840628e+10 | G54: =F54/$F$59 -> 0 | H54: =F54/$F$12 -> 0
C55: Налог на прибыль | D55: 0.25 | F55: =M55 -> 6.7334264e+09 | G55: =F55/$F$59 -> 0.067319223 | H55: =F55/$F$12 -> 0.057 | J55: =F12-F59-F65 -> 8.1057099e+09 | K55: =J55*D55 -> 2.0264275e+09 | M55: =F12*5.7% -> 6.7334264e+09
B56: ПФ | F56: =SUM(F57:F58) -> 1.4386244e+10 | G56: =F56/$F$59 -> 0.14383031
C57: ='CF1 '!A107 -> Проценты начисленные | F57: =-'CF1 '!C107 -> 1.4386244e+10
C59: ИТОГО Расходы | F59: =F16+F20+F23+F30+F50+F54+F55+F56 -> 1.0002234e+11 | G59: =G16+G20+G23+G30+G50+G54 -> 0.78885047
C61: ФИНРЕЗ | F61: =F12-F59 -> 1.8107944e+10 | G61: =G16+G20+G23+G30+G50+G54+G55+G56 -> 1 | H61: =F61/F12 -> 0.1532879
C63: NPV | F63: =F61 -> 1.8107944e+10 | G63: какой %, какой должен быть чтобы проект был эффективным?
C64: IRR Рентабельность проекта | F64: =F63/F59 -> 0.18103899
C65: Собственный капитал | D65: 0.1 | F65: =F59*D65 -> 1.0002234e+10
C66: Рентабельность собственного капитала | F66: =F63/F65 -> 1.8103899
C67: Проектное финансирование | D67: =F67/F59 -> 0.83682442 | F67: =F30+F23+F17+F50+F53 -> 8.370114e+10
C68: Банковские расходы | D68: 0.15 | F68: =F67*D68 -> 1.2555171e+10
C69: Себестоимость 1м2 | F69: =F59/E5 -> 2964609.9
C70: Средняя стоимость старта продаж | F70: =D5 -> 573799.03
C71: Наценка | F71: =(F70-F69)/F69 -> -0.80645041
C73: Непрогнозтруемая выручка | D73: =E73/F12 -> 0.13063627 | E73: =SUM('План продаж'!Q25:S25) -> 1.54321e+10
C74: Прогнозируемая выручка | D74: =E74/F12 -> 0.86936373 | E74: =F12-E73 -> 1.0269819e+11
C75: Дефицит чистой прибыли на момент РнВ | E75: =F63-E73 -> 2.6758441e+09

Sheet CF1 
A1: Ед. изм. - тыс. руб. | C1: ПИР 30.06.27 | F1: РнС | AB1: РнВ | AH1: конец продаж
E2: 46022 | F2: =EDATE(E2,3) -> 46112 | G2: =EOMONTH(F2,3) -> 46203 | H2: =EOMONTH(G2,3) -> 46295 | I2: =EOMONTH(H2,3) -> 46387 | J2: =EOMONTH(I2,3) -> 46477 | K2: =EOMONTH(J2,3) -> 46568 | L2: =EOMONTH(K2,3) -> 46660 | M2: =EOMONTH(L2,3) -> 46752 | N2: =EOMONTH(M2,3) -> 46843 | ... AS2: =EOMONTH(AR2,3) -> 49674
A3: Кол-во дней | F3: =F2-E2 -> 90 | G3: =G2-F2 -> 91 | H3: =H2-G2 -> 92 | I3: =I2-H2 -> 92 | J3: =J2-I2 -> 90 | K3: =K2-J2 -> 91 | L3: =L2-K2 -> 92 | M3: =M2-L2 -> 92 | ... AS3: =AS2-AR2 -> 92
A4: Начало стройки | D4: =ТЭПы!C7 -> 4 кв 2025 | F4: =IF(F2=$D$4,1,0) -> 0 | G4: =IF(G2=$D$4,1,0) -> 0 | H4: =IF(H2=$D$4,1,0) -> 0 | I4: =IF(I2=$D$4,1,0) -> 0 | J4: =IF(J2=$D$4,1,0) -> 0 | K4: =IF(K2=$D$4,1,0) -> 0 | L4: =IF(L2=$D$4,1,0) -> 0 | M4: =IF(M2=$D$4,1,0) -> 0 | ... AS4: =IF(AS2=$D$4,1,0) -> 0
A5: Завершение стройки | D5: =ТЭПы!C9 -> 1 кв 2032 | F5: =IF(AND(F2>=$D$4,F2<=$D$5),1,0) -> 0 | G5: =IF(AND(G2>=$D$4,G2<=$D$5),1,0) -> 0 | H5: =IF(AND(H2>=$D$4,H2<=$D$5),1,0) -> 0 | I5: =IF(AND(I2>=$D$4,I2<=$D$5),1,0) -> 0 | J5: =IF(AND(J2>=$D$4,J2<=$D$5),1,0) -> 0 | K5: =IF(AND(K2>=$D$4,K2<=$D$5),1,0) -> 0 | L5: =IF(AND(L2>=$D$4,L2<=$D$5),1,0) -> 0 | M5: =IF(AND(M2>=$D$4,M2<=$D$5),1,0) -> 0 | ... AS5: =IF(AND(AS2>=$D$4,AS2<=$D$5),1,0) -> 0
A6: Раскрытие Escrow | D6: =ТЭПы!C12 -> 2 кв 2032 | F6: =IF(F2=$D$6,1,0) -> 0 | G6: =IF(G2=$D$6,1,0) -> 0 | H6: =IF(H2=$D$6,1,0) -> 0 | I6: =IF(I2=$D$6,1,0) -> 0 | J6: =IF(J2=$D$6,1,0) -> 0 | K6: =IF(K2=$D$6,1,0) -> 0 | L6: =IF(L2=$D$6,1,0) -> 0 | M6: =IF(M2=$D$6,1,0) -> 0 | ... AA6: =IF(AA2=$D$6,1,0) -> 0 | AB6: 1 | AC6: 0 | AD6: 0 | AE6: 0 | AF6: 0 | AG6: =IF(AG2=$D$6,1,0) -> 0 | AH6: =IF(AH2=$D$6,1,0) -> 0 | AI6: =IF(AI2=$D$6,1,0) -> 0 | AJ6: =IF(AJ2=$D$6,1,0) -> 0 | AK6: =IF(AK2=$D$6,1,0) -> 0 | AL6: =IF(AL2=$D$6,1,0) -> 0 | AM6: =IF(AM2=$D$6,1,0) -> 0 | AN6: =IF(AN2=$D$6,1,0) -> 0 | ... AS6: =IF(AS2=$D$6,1,0) -> 0
A7: Год строительства | F7: 1 | G7: 1 | H7: 1 | I7: 1 | J7: 2 | K7: 2 | L7: 2 | M7: 2 | N7: 3 | O7: 3 | P7: 3 | Q7: 3 | R7: 4 | S7: 4 | T7: 4 | U7: 4 | V7: 5 | W7: 5 | X7: 5 | Y7: 5 | Z7: 6 | AA7: 6 | AB7: 6 | AC7: 6 | AD7: =ROUNDUP(SUM($E$5:AD$5)/4,0)*AD5 -> 0 | AE7: =ROUNDUP(SUM($E$5:AE$5)/4,0)*AE5 -> 0 | AF7: =ROUNDUP(SUM($E$5:AF$5)/4,0)*AF5 -> 0 | AG7: =ROUNDUP(SUM($E$5:AG$5)/4,0)*AG5 -> 0 | AH7: =ROUNDUP(SUM($E$5:AH$5)/4,0)*AH5 -> 0 | AI7: =ROUNDUP(SUM($E$5:AI$5)/4,0)*AI5 -> 0 | AJ7: =ROUNDUP(SUM($E$5:AJ$5)/4,0)*AJ5 -> 0 | AK7: =ROUNDUP(SUM($E$5:AK$5)/4,0)*AK5 -> 0 | ... AS7: =ROUNDUP(SUM($E$5:AS$5)/4,0)*AS5 -> 0
A8: Продажи по escrow | F8: =IF(F2<=$D$6,1,0) -> 1 | G8: =IF(G2<=$D$6,1,0) -> 1 | H8: =IF(H2<=$D$6,1,0) -> 1 | I8: =IF(I2<=$D$6,1,0) -> 1 | J8: =IF(J2<=$D$6,1,0) -> 1 | K8: =IF(K2<=$D$6,1,0) -> 1 | L8: =IF(L2<=$D$6,1,0) -> 1 | M8: =IF(M2<=$D$6,1,0) -> 1 | ... AA8: =IF(AA2<=$D$6,1,0) -> 1 | AB8: 0 | AC8: 0 | AD8: 0 | AE8: 0 | AF8: 0 | AG8: 0 | AH8: 0 | AI8: 0 | AJ8: 0 | AK8: 0 | AL8: 0 | AM8: 0 | AN8: 0 | AO8: 0 | AP8: 0 | AQ8: 0 | AR8: 0 | AS8: 0
A9: Продажи по ДКП | F9: =IF(F2>$D$6,1,0) -> 0 | G9: =IF(G2>$D$6,1,0) -> 0 | H9: =IF(H2>$D$6,1,0) -> 0 | I9: =IF(I2>$D$6,1,0) -> 0 | J9: =IF(J2>$D$6,1,0) -> 0 | K9: =IF(K2>$D$6,1,0) -> 0 | L9: =IF(L2>$D$6,1,0) -> 0 | M9: =IF(M2>$D$6,1,0) -> 0 | ... AS9: =IF(AS2>$D$6,1,0) -> 0
A10: Площадь в ГНС, кв. м | D10: =ТЭПы!C19 -> 221967
A11: Продаваемая площадь, кв. м | D11: =ТЭПы!C22+ТЭПы!C23 -> 153882
C13: Итого
A15: ДОХОДЫ | B15: ='Бюджет '!F12 -> 1.1813029e+11 | C15: =SUM(F15:AS15) -> 1.1751409e+11 | F15: ='План продаж'!E25 -> 4.1843962e+09 | G15: ='План продаж'!F25 -> 1.3274389e+09 | H15: ='План продаж'!G25 -> 9.108064e+08 | I15: ='План продаж'!H25 -> 1.1457736e+09 | J15: ='План продаж'!I25 -> 9.665167e+08 | K15: ='План продаж'!J25 -> 2.5065255e+09 | L15: ='План продаж'!K25 -> 2.9827652e+09 | M15: ='План продаж'!L25 -> 3.6220998e+09 | ... AH15: ='План продаж'!AG25 -> 1.0774015e+09
A18: РАСХОДЫ | B18: =+B20+B23+B27+B40+B77 -> 7.6905419e+10 | C18: =SUM(F18:AS18) -> 7.6888564e+10 | D18: =C18-D19+C81-C107 -> 8.1982972e+10 | F18: =SUM(F20,F23,F27,F40,F77) -> 2.0215311e+09 | G18: =SUM(G20,G23,G27,G40,G77) -> 6.8917525e+08 | H18: =SUM(H20,H23,H27,H40,H77) -> 1.7393666e+09 | I18: =SUM(I20,I23,I27,I40,I77) -> 1.7705194e+09 | J18: =SUM(J20,J23,J27,J40,J77) -> 1.7705194e+09 | K18: =SUM(K20,K23,K27,K40,K77) -> 3.1672708e+09 | L18: =SUM(L20,L23,L27,L40,L77) -> 2.3408241e+09 | M18: =SUM(M20,M23,M27,M40,M77) -> 3.6080485e+09 | ... AS18: =SUM(AS20,AS23,AS27,AS40,AS77) -> 0
D19: =SUM(I18:N18) -> 1.6036933e+10
A20: Вход в проект | B20: =B21 -> 1330355898 | C20: =SUM(F20:AS20) -> 1330355898 | F20: =F21 -> 1330355898 | G20: =G21 -> 0 | H20: =H21 -> 0 | I20: =I21 -> 0 | J20: =J21 -> 0 | K20: =K21 -> 0 | L20: =L21 -> 0 | M20: =M21 -> 0 | ... AS20: =AS21 -> 0
A21: Покупка и формирование актива, агентские , diudill | B21: ='Бюджет '!F16 -> 1330355898 | C21: =SUM(F21:AS21) -> 1330355898 | F21: =F22*$B$21 -> 1330355898 | G21: =G22*$B$21 -> 0 | H21: =H22*$B$21 -> 0 | I21: =I22*$B$21 -> 0 | J21: =J22*$B$21 -> 0 | K21: =K22*$B$21 -> 0 | L21: =L22*$B$21 -> 0 | M21: =M22*$B$21 -> 0 | ... AS21: =AS22*$B$21 -> 0
A22: Проставить темп,% | C22: =SUM(F22:AS22) -> 1 | F22: 1 | G22: 0 | I22: 0 | J22: 0 | O22: 0 | Q22: 0
A23: Земельно-имущественные отношения | B23: =B24+B25 -> 1.9349595e+09 | C23: =SUM(F23:AS23) -> 1.9349595e+09 | F23: =SUM(F24,F25) -> 28452570 | G23: =SUM(G24,G25) -> 28452570 | H23: =SUM(H24,H25) -> 28452570 | I23: =SUM(I24,I25) -> 28452570 | J23: =SUM(J24,J25) -> 28452570 | K23: =SUM(K24,K25) -> 1.1382876e+09 | L23: =SUM(L24,L25) -> 28452570 | M23: =SUM(M24,M25) -> 28452570 | ... AS23: =SUM(AS24,AS25) -> 0
A24: Аренда/налог ЗУ | B24: ='Бюджет '!F21 -> 8.2512453e+08 | C24: =SUM(F24:AS24) -> 8.2512453e+08 | F24: =$B$24/ТЭПы!$C$5/4 -> 28452570 | G24: =$B$24/ТЭПы!$C$5/4 -> 28452570 | H24: =$B$24/ТЭПы!$C$5/4 -> 28452570 | I24: =$B$24/ТЭПы!$C$5/4 -> 28452570 | J24: =$B$24/ТЭПы!$C$5/4 -> 28452570 | K24: =$B$24/ТЭПы!$C$5/4 -> 28452570 | L24: =$B$24/ТЭПы!$C$5/4 -> 28452570 | M24: =$B$24/ТЭПы!$C$5/4 -> 28452570 | ... AH24: =$B$24/ТЭПы!$C$5/4 -> 28452570
A25: Плата за изменение ВРИ | B25: ='Бюджет '!F22 -> 1109835000 | C25: =SUM(F25:AS25) -> 1109835000 | F25: =F26*$B$25 -> 0 | G25: =G26*$B$25 -> 0 | H25: =H26*$B$25 -> 0 | I25: =I26*$B$25 -> 0 | J25: =J26*$B$25 -> 0 | K25: =K26*$B$25 -> 1109835000 | L25: =L26*$B$25 -> 0 | M25: =M26*$B$25 -> 0 | ... AS25: =AS26*$B$25 -> 0
A26: Проставить темп,% | C26: =SUM(F26:AS26) -> 1 | K26: 1 | N26: 0 | O26: 0
A27: ПИР и ИРД | B27: =B28+B30+B32+B34+B36+B38 -> 2.0131747e+09 | C27: =SUM(F27:AS27) -> 2.0131747e+09 | F27: =SUM(F28,F30,F32,F34,F36,F38) -> 3.7757034e+08 | G27: =SUM(G28,G30,G32,G34,G36,G38) -> 3.7557034e+08 | H27: =SUM(H28,H30,H32,H34,H36,H38) -> 0 | I27: =SUM(I28,I30,I32,I34,I36,I38) -> 0 | J27: =SUM(J28,J30,J32,J34,J36,J38) -> 0 | K27: =SUM(K28,K30,K32,K34,K36,K38) -> 0 | L27: =SUM(L28,L30,L32,L34,L36,L38) -> 0 | M27: =SUM(M28,M30,M32,M34,M36,M38) -> 6.3001699e+08 | ... AS27: =SUM(AS28,AS30,AS32,AS34,AS36,AS38) -> 0
A28: Компенсация городу | B28: ='Бюджет '!F24 -> 1.260034e+09 | C28: =SUM(F28:AS28) -> 1.260034e+09 | F28: =F29*$B$28 -> 0 | G28: =G29*$B$28 -> 0 | H28: =H29*$B$28 -> 0 | I28: =I29*$B$28 -> 0 | J28: =J29*$B$28 -> 0 | K28: =K29*$B$28 -> 0 | L28: =L29*$B$28 -> 0 | M28: =M29*$B$28 -> 6.3001699e+08 | ... AS28: =AS29*$B$28 -> 0
A29: Проставить темп,% | C29: =SUM(F29:AS29) -> 1 | M29: 0.5 | N29: 0.5
A30: Получение ИРД (ППТ,ГПЗУ) | B30: ='Бюджет '!F25 -> 0 | C30: =SUM(F30:AS30) -> 0 | F30: =F31*$B$30 -> 0 | G30: =G31*$B$30 -> 0 | H30: =H31*$B$30 -> 0 | I30: =I31*$B$30 -> 0 | J30: =J31*$B$30 -> 0 | K30: =K31*$B$30 -> 0 | L30: =L31*$B$30 -> 0 | M30: =M31*$B$30 -> 0 | ... AS30: =AS31*$B$30 -> 0
A31: Проставить темп,% | C31: =SUM(F31:AS31) -> 1 | I31: 0 | J31: 0 | K31: 0 | L31: 0 | M31: =1/8 -> 0.125 | N31: 0.125 | O31: 0.125 | P31: 0.125 | T31: 0 | U31: 0 | V31: 0 | X31: 0.25 | Y31: 0.25
A32: Проектирование объектов стадия П | B32: ='Бюджет '!F26 -> 751140673 | C32: =SUM(F32:AS32) -> 751140673 | F32: =F33*$B$32 -> 3.7557034e+08 | G32: =G33*$B$32 -> 3.7557034e+08 | H32: =H33*$B$32 -> 0 | I32: =I33*$B$32 -> 0 | J32: =J33*$B$32 -> 0 | K32: =K33*$B$32 -> 0 | L32: =L33*$B$32 -> 0 | M32: =M33*$B$32 -> 0 | ... AS32: =AS33*$B$32 -> 0
A33: Проставить темп,% | C33: =SUM(F33:AS33) -> 1 | F33: 0.5 | G33: 0.5
A34: Проектирование объектов стадия РД | B34: ='Бюджет '!F27 -> 0 | C34: =SUM(F34:AS34) -> 0 | F34: =F35*$B$34 -> 0 | G34: =G35*$B$34 -> 0 | H34: =H35*$B$34 -> 0 | I34: =I35*$B$34 -> 0 | J34: =J35*$B$34 -> 0 | K34: =K35*$B$34 -> 0 | L34: =L35*$B$34 -> 0 | M34: =M35*$B$34 -> 0 | ... AS34: =AS35*$B$34 -> 0
A35: Проставить темп,% | C35: =SUM(F35:AS35) -> 0
A36: Инженерные изыскания (опер деятельность) | B36: ='Бюджет '!F28 -> 0 | C36: =SUM(F36:AS36) -> 0 | F36: =F37*$B$36 -> 0 | G36: =G37*$B$36 -> 0 | H36: =H37*$B$36 -> 0 | I36: =I37*$B$36 -> 0 | J36: =J37*$B$36 -> 0 | K36: =K37*$B$36 -> 0 | L36: =L37*$B$36 -> 0 | M36: =M37*$B$36 -> 0 | ... AS36: =AS37*$B$36 -> 0
A37: Проставить темп,% | C37: =SUM(F37:AS37) -> 0
A38: Предпроектные проработки | B38: ='Бюджет '!F29 -> 2000000 | C38: =SUM(F38:AS38) -> 2000000 | F38: =F39*$B$38 -> 2000000 | G38: =G39*$B$38 -> 0 | H38: =H39*$B$38 -> 0 | I38: =I39*$B$38 -> 0 | J38: =J39*$B$38 -> 0 | K38: =K39*$B$38 -> 0 | L38: =L39*$B$38 -> 0 | M38: =M39*$B$38 -> 0 | ... AS38: =AS39*$B$38 -> 0
A39: Проставить темп,% | C39: =SUM(F39:AS39) -> 1 | F39: 1 | G39: 0 | H39: 0
A40: САРЕХ | B40: =B41+B43+B45+B47+B49+B51+B53+B57+B55+B59+B61+B63+B65+B67+B69+B71+B73+B75 -> 6.4759193e+10 | C40: =SUM(F40:AS40) -> 6.4742338e+10 | F40: =SUM(F41,F43,F45,F47,F49,F51,F53,F55,F57,F59,F61,F63,F65,F67,F69,F71,F73,F75) -> 2.8515234e+08 | G40: =SUM(G41,G43,G45,G47,G49,G51,G53,G55,G57,G59,G61,G63,G65,G67,G69,G71,G73,G75) -> 2.8515234e+08 | H40: =SUM(H41,H43,H45,H47,H49,H51,H53,H55,H57,H59,H61,H63,H65,H67,H69,H71,H73,H75) -> 1.710914e+09 | I40: =SUM(I41,I43,I45,I47,I49,I51,I53,I55,I57,I59,I61,I63,I65,I67,I69,I71,I73,I75) -> 1.7420668e+09 | J40: =SUM(J41,J43,J45,J47,J49,J51,J53,J55,J57,J59,J61,J63,J65,J67,J69,J71,J73,J75) -> 1.7420668e+09 | K40: =SUM(K41,K43,K45,K47,K49,K51,K53,K55,K57,K59,K61,K63,K65,K67,K69,K71,K73,K75) -> 2.0289833e+09 | L40: =SUM(L41,L43,L45,L47,L49,L51,L53,L55,L57,L59,L61,L63,L65,L67,L69,L71,L73,L75) -> 2.3123715e+09 | M40: =SUM(M41,M43,M45,M47,M49,M51,M53,M55,M57,M59,M61,M63,M65,M67,M69,M71,M73,M75) -> 2.6566712e+09 | ... AS40: =SUM(AS41,AS43,AS45,AS47,AS49,AS51,AS53,AS55,AS57,AS59,AS61,AS63,AS65,AS67,AS69,AS71,AS73,AS75) -> 0
A41: Подготовка площадки (включая снос) | B41: ='Бюджет '!F31 -> 141554585 | C41: =SUM(F41:AS41) -> 141554585 | F41: =F42*$B$41 -> 0 | G41: =G42*$B$41 -> 0 | H41: =H42*$B$41 -> 0 | I41: =I42*$B$41 -> 28310917 | J41: =J42*$B$41 -> 28310917 | K41: =K42*$B$41 -> 28310917 | L41: =L42*$B$41 -> 28310917 | M41: =M42*$B$41 -> 28310917 | ... AS41: =AS42*$B$41 -> 0
A42: Проставить темп,% | C42: =SUM(F42:AS42) -> 1 | I42: 0.2 | J42: 0.2 | K42: 0.2 | L42: 0.2 | M42: 0.2 | N42: 0 | O42: 0
A43: СМР надземной части (в т.ч. стилобат) | B43: ='Бюджет '!F32 -> 52782616084 | C43: =SUM(F43:AS43) -> 5.2782616e+10 | F43: =F44*$B$43 -> 2.6391308e+08 | G43: =G44*$B$43 -> 2.6391308e+08 | H43: =H44*$B$43 -> 1.5834785e+09 | I43: =I44*$B$43 -> 1.5834785e+09 | J43: =J44*$B$43 -> 1.5834785e+09 | K43: =K44*$B$43 -> 1.5834785e+09 | L43: =L44*$B$43 -> 2.1113046e+09 | M43: =M44*$B$43 -> 2.1113046e+09 | ... AS43: =AS44*$B$43 -> 0
A44: Проставить темп,% | C44: =SUM(F44:AS44) -> 1 | F44: 0.005 | G44: 0.005 | H44: 0.03 | I44: 0.03 | J44: 0.03 | K44: 0.03 | L44: 0.04 | M44: 0.04 | N44: 0.04 | O44: 0.04 | P44: 0.05 | Q44: 0.07 | R44: 0.07 | S44: 0.07 | T44: 0.07 | U44: 0.07 | V44: 0.07 | W44: 0.07 | X44: 0.07 | Y44: 0.05 | Z44: 0.05
A45: СМР подземной части | B45: ='Бюджет '!F33 -> 0 | C45: =SUM(F45:AS45) -> 0 | F45: =F46*$B$45 -> 0 | G45: =G46*$B$45 -> 0 | H45: =H46*$B$45 -> 0 | I45: =I46*$B$45 -> 0 | J45: =J46*$B$45 -> 0 | K45: =K46*$B$45 -> 0 | L45: =L46*$B$45 -> 0 | M45: =M46*$B$45 -> 0 | ... AS45: =AS46*$B$45 -> 0
A46: Проставить темп,% | C46: =SUM(F46:AS46) -> 1 | M46: 0.3 | N46: 0.3 | O46: 0.3 | P46: 0.1
A47: Отделка МОП | B47: ='Бюджет '!F34 -> 0 | C47: =SUM(F47:AS47) -> 0 | F47: =F48*$B$47 -> 0 | G47: =G48*$B$47 -> 0 | H47: =H48*$B$47 -> 0 | I47: =I48*$B$47 -> 0 | J47: =J48*$B$47 -> 0 | K47: =K48*$B$47 -> 0 | L47: =L48*$B$47 -> 0 | M47: =M48*$B$47 -> 0 | ... AS47: =AS48*$B$47 -> 0
A48: Проставить темп,% | C48: =SUM(F48:AS48) -> 1 | Z48: 0.5 | AA48: 0.5
A49: ТУ и плата за тех. присоединение | B49: ='Бюджет '!F35 -> 1.1476657e+09 | C49: =SUM(F49:AS49) -> 1.1476657e+09 | F49: =F50*$B$49 -> 0 | G49: =G50*$B$49 -> 0 | H49: =H50*$B$49 -> 0 | I49: =I50*$B$49 -> 0 | J49: =J50*$B$49 -> 0 | K49: =K50*$B$49 -> 2.8691643e+08 | L49: =L50*$B$49 -> 0 | M49: =M50*$B$49 -> 0 | ... AS49: =AS50*$B$49 -> 0
A50: Проставить темп,% | C50: =SUM(F50:AS50) -> 1 | K50: 0.25 | O50: 0 | P50: 0 | S50: 0.25 | T50: 0.25 | Y50: 0.25 | Z50: 0 | AF50: 0 | AG50: 0 | AH50: 0
A51: Наружные сети и сооружения | B51: ='Бюджет '!F36 -> 1.1476657e+09 | C51: =SUM(F51:AS51) -> 1.1476657e+09 | F51: =F52*$B$51 -> 0 | G51: =G52*$B$51 -> 0 | H51: =H52*$B$51 -> 0 | I51: =I52*$B$51 -> 0 | J51: =J52*$B$51 -> 0 | K51: =K52*$B$51 -> 0 | L51: =L52*$B$51 -> 0 | M51: =M52*$B$51 -> 3.4429972e+08 | ... AS51: =AS52*$B$51 -> 0
A52: Проставить темп,% | C52: =SUM(F52:AS52) -> 1 | M52: 0.3 | N52: 0.3 | V52: 0.3 | W52: 0.1
A53: Благоустройство, объекты транспортного хозяйства | B53: ='Бюджет '!F37 -> 1355940 | C53: =SUM(F53:AS53) -> 1355940 | F53: =F54*$B$53 -> 0 | G53: =G54*$B$53 -> 0 | H53: =H54*$B$53 -> 0 | I53: =I54*$B$53 -> 0 | J53: =J54*$B$53 -> 0 | K53: =K54*$B$53 -> 0 | L53: =L54*$B$53 -> 0 | M53: =M54*$B$53 -> 0 | ... AS53: =AS54*$B$53 -> 0
A54: Проставить темп,% | C54: =SUM(F54:AS54) -> 1 | W54: 0.25 | X54: 0.25 | Y54: 0.25 | Z54: 0.25
A55: Прочие СМР | B55: ='Бюджет '!F39 -> 16904953 | C55: =SUM(F55:AS55) -> 0 | F55: =F56*$B$55 -> 0 | G55: =G56*$B$55 -> 0 | H55: =H56*$B$55 -> 0 | I55: =I56*$B$55 -> 0 | J55: =J56*$B$55 -> 0 | K55: =K56*$B$55 -> 0 | L55: =L56*$B$55 -> 0 | M55: =M56*$B$55 -> 0 | ... AS55: =AS56*$B$55 -> 0
A56: Проставить темп,% | C56: =SUM(F56:AS56) -> 0
A57: Иные расходы на проекты (охрана, содержание площадки) | B57: ='Бюджет '!F40 -> 56837556 | C57: =SUM(F57:AS57) -> 56837556 | F57: =F58*$B$57 -> 0 | G57: =G58*$B$57 -> 0 | H57: =H58*$B$57 -> 0 | I57: =I58*$B$57 -> 2841877.8 | J57: =J58*$B$57 -> 2841877.8 | K57: =K58*$B$57 -> 2841877.8 | L57: =L58*$B$57 -> 2841877.8 | M57: =M58*$B$57 -> 2841877.8 | ... AS57: =AS58*$B$57 -> 0
A58: Проставить темп,% | C58: =SUM(F58:AS58) -> 1 | I58: 0.05 | J58: 0.05 | K58: 0.05 | L58: 0.05 | M58: 0.05 | N58: 0.05 | O58: 0.05 | P58: 0.05 | Q58: 0.05 | R58: 0.05 | S58: 0.05 | T58: 0.05 | U58: 0.05 | V58: 0.05 | W58: 0.05 | X58: 0.05 | Y58: 0.05 | Z58: 0.05 | AA58: 0.05 | AB58: 0.05
A59: Расходы по вводу в эксплуатацию | B59: ='Бюджет '!F41 -> 0 | C59: =SUM(F59:AS59) -> 0 | F59: =F60*$B$59 -> 0 | G59: =G60*$B$59 -> 0 | H59: =H60*$B$59 -> 0 | I59: =I60*$B$59 -> 0 | J59: =J60*$B$59 -> 0 | K59: =K60*$B$59 -> 0 | L59: =L60*$B$59 -> 0 | M59: =M60*$B$59 -> 0 | ... AS59: =AS60*$B$59 -> 0
A60: Проставить темп,% | C60: =SUM(F60:AS60) -> 1 | V60: 0.2 | W60: 0.2 | X60: 0.2 | Y60: 0.2 | Z60: 0.2
A61: Непредвиденные расходы | B61: ='Бюджет '!F42 -> 202839.89 | C61: =SUM(F61:AS61) -> 252738.51 | F61: =F62*$B$61 -> 1014.1995 | G61: =G62*$B$61 -> 1014.1995 | H61: =H62*$B$61 -> 6085.1968 | I61: =I62*$B$61 -> 6085.1968 | J61: =J62*$B$61 -> 6085.1968 | K61: =K62*$B$61 -> 6085.1968 | L61: =L62*$B$61 -> 8113.5957 | M61: =M62*$B$61 -> 8113.5957 | ... AS61: =AS62*$B$61 -> 0
A62: Проставить темп,% | C62: =SUM(F62:AS62) -> 1.246 | F62: =F44 -> 0.005 | G62: =G44 -> 0.005 | H62: =H44 -> 0.03 | I62: =I44 -> 0.03 | J62: =J44 -> 0.03 | K62: =K44 -> 0.03 | L62: =L44 -> 0.04 | M62: =M44 -> 0.04 | N62: =N44 -> 0.04 | O62: 0.0714 | P62: 0.0714 | Q62: 0.0714 | R62: 0.0714 | S62: 0.141 | T62: 0.141 | U62: 0.0714 | V62: 0.0714 | W62: 0.0714 | X62: 0.0714 | Y62: 0.0714 | Z62: 0.0714 | AA62: =AA44 -> 0 | AB62: =AB44 -> 0 | AC62: =AC44 -> 0 | AD62: =AD44 -> 0 | AE62: =AE44 -> 0 | AF62: =AF44 -> 0 | AG62: =AG44 -> 0 | AH62: =AH44 -> 0 | ... AS62: =AS44 -> 0
A63: Услуги технического заказчика | B63: ='Бюджет '!F43 -> 2383139493 | C63: =SUM(F63:AS63) -> 2383139493 | F63: =F64*$B$63 -> 11915697 | G63: =G64*$B$63 -> 11915697 | H63: =H64*$B$63 -> 71494185 | I63: =I64*$B$63 -> 71494185 | J63: =J64*$B$63 -> 71494185 | K63: =K64*$B$63 -> 71494185 | L63: =L64*$B$63 -> 95325580 | M63: =M64*$B$63 -> 95325580 | ... AS63: =AS64*$B$63 -> 0
A64: Проставить темп,% | C64: =SUM(F64:AS64) -> 1 | F64: 0.005 | G64: 0.005 | H64: 0.03 | I64: 0.03 | J64: 0.03 | K64: 0.03 | L64: 0.04 | M64: 0.04 | N64: 0.04 | O64: 0.04 | P64: 0.05 | Q64: 0.07 | R64: 0.07 | S64: 0.07 | T64: 0.07 | U64: 0.07 | V64: 0.07 | W64: 0.07 | X64: 0.07 | Y64: 0.05 | Z64: 0.05 | AA64: =AA44 -> 0 | AB64: =AB44 -> 0 | AC64: =AC44 -> 0 | AD64: =AD44 -> 0 | AE64: =AE44 -> 0 | AF64: =AF44 -> 0 | AG64: =AG44 -> 0 | AH64: =AH44 -> 0 | ... AS64: =AS44 -> 0
A65: Авторский надзор | B65: ='Бюджет '!F44 -> 0 | C65: =SUM(F65:AS65) -> 0 | F65: =F66*$B$65 -> 0 | G65: =G66*$B$65 -> 0 | H65: =H66*$B$65 -> 0 | I65: =I66*$B$65 -> 0 | J65: =J66*$B$65 -> 0 | K65: =K66*$B$65 -> 0 | L65: =L66*$B$65 -> 0 | M65: =M66*$B$65 -> 0 | ... AS65: =AS66*$B$65 -> 0
A66: Проставить темп,% | C66: =SUM(F66:AS66) -> 0
A67: Мониторинг окружающей застройки | B67: ='Бюджет '!F45 -> 88670039 | C67: =SUM(F67:AS67) -> 88670039 | F67: =F68*$B$67 -> 0 | G67: =G68*$B$67 -> 0 | H67: =H68*$B$67 -> 0 | I67: =I68*$B$67 -> 0 | J67: =J68*$B$67 -> 0 | K67: =K68*$B$67 -> 0 | L67: =L68*$B$67 -> 0 | M67: =M68*$B$67 -> 0 | ... AS67: =AS68*$B$67 -> 0
A68: Проставить темп,% | C68: =SUM(F68:AS68) -> 1 | Y68: 0.25 | Z68: 0.25 | AA68: 0.25 | AB68: 0.25
A69: Технический надзор | B69: ='Бюджет '!F46 -> 0 | C69: =SUM(F69:AS69) -> 0 | F69: =F70*$B$69 -> 0 | G69: =G70*$B$69 -> 0 | H69: =H70*$B$69 -> 0 | I69: =I70*$B$69 -> 0 | J69: =J70*$B$69 -> 0 | K69: =K70*$B$69 -> 0 | L69: =L70*$B$69 -> 0 | M69: =M70*$B$69 -> 0 | ... AS69: =AS70*$B$69 -> 0
A70: Проставить темп,% | C70: =SUM(F70:AS70) -> 0
A71: Социальные объекты (отдельно возводимые) | B71: ='Бюджет '!F47 -> 5.1280701e+09 | C71: =SUM(F71:AS71) -> 5.1280701e+09 | F71: =F72*$B$71 -> 0 | G71: =G72*$B$71 -> 0 | H71: =H72*$B$71 -> 0 | I71: =I72*$B$71 -> 0 | J71: =J72*$B$71 -> 0 | K71: =K72*$B$71 -> 0 | L71: =L72*$B$71 -> 0 | M71: =M72*$B$71 -> 0 | ... AS71: =AS72*$B$71 -> 0
A72: Проставить темп,% | C72: =SUM(F72:AS72) -> 1 | V72: 0 | W72: 0.25 | X72: 0.25 | Y72: 0.25 | Z72: 0.25
A73: Вознаграждение за управление проектом | B73: ='Бюджет '!F48 -> 1850054797 | C73: =SUM(F73:AS73) -> 1.8500548e+09 | F73: =F74*$B$73 -> 9250274 | G73: =G74*$B$73 -> 9250274 | H73: =H74*$B$73 -> 55501644 | I73: =I74*$B$73 -> 55501644 | J73: =J74*$B$73 -> 55501644 | K73: =K74*$B$73 -> 55501644 | L73: =L74*$B$73 -> 74002192 | M73: =M74*$B$73 -> 74002192 | ... AS73: =AS74*$B$73 -> 0
A74: Проставить темп,% | C74: =SUM(F74:AS74) -> 1 | F74: =F44 -> 0.005 | G74: =G44 -> 0.005 | H74: =H44 -> 0.03 | I74: =I44 -> 0.03 | J74: =J44 -> 0.03 | K74: =K44 -> 0.03 | L74: =L44 -> 0.04 | M74: =M44 -> 0.04 | ... AS74: =AS44 -> 0
A75: Содержание застройщика | B75: ='Бюджет '!F49 -> 14454851 | C75: =SUM(F75:AS75) -> 14454851 | F75: =F76*$B$75 -> 72274.254 | G75: =G76*$B$75 -> 72274.254 | H75: =H76*$B$75 -> 433645.53 | I75: =I76*$B$75 -> 433645.53 | J75: =J76*$B$75 -> 433645.53 | K75: =K76*$B$75 -> 433645.53 | L75: =L76*$B$75 -> 578194.03 | M75: =M76*$B$75 -> 578194.03 | ... AS75: =AS76*$B$75 -> 0
A76: Проставить темп,% | C76: =SUM(F76:AS76) -> 1 | F76: 0.005 | G76: 0.005 | H76: 0.03 | I76: 0.03 | J76: 0.03 | K76: 0.03 | L76: 0.04 | M76: 0.04 | N76: 0.04 | O76: 0.04 | P76: 0.05 | Q76: 0.07 | R76: 0.07 | S76: 0.07 | T76: 0.07 | U76: 0.07 | V76: 0.07 | W76: 0.07 | X76: 0.07 | Y76: 0.05 | Z76: 0.05
A77: ОРЕХ | B77: =SUM(E77:AR77) -> 6.8677366e+09 | C77: =SUM(F77:AS77) -> 6.8677366e+09 | F77: =SUM(F78:F79) -> 0 | G77: =SUM(G78:G79) -> 0 | H77: =SUM(H78:H79) -> 0 | I77: =SUM(I78:I79) -> 0 | J77: =SUM(J78:J79) -> 0 | K77: =SUM(K78:K79) -> 0 | L77: =SUM(L78:L79) -> 0 | M77: =SUM(M78:M79) -> 2.9290773e+08 | ... AS77: =SUM(AS78:AS79) -> 0
A78: Брокеридж | B78: ='Бюджет '!F52 -> 4.1345601e+09 | C78: =SUM(G78:AS78) -> 2.7331765e+09 | M78: ='План продаж'!E25*'Бюджет '!$D$52 -> 1.4645387e+08 | N78: ='План продаж'!F25*'Бюджет '!$D$52 -> 46460363 | O78: ='План продаж'!G25*'Бюджет '!$D$52 -> 31878224 | P78: ='План продаж'!H25*'Бюджет '!$D$52 -> 40102075 | Q78: ='План продаж'!I25*'Бюджет '!$D$52 -> 33828084 | R78: ='План продаж'!J25*'Бюджет '!$D$52 -> 87728393 | S78: ='План продаж'!K25*'Бюджет '!$D$52 -> 1.0439678e+08 | T78: ='План продаж'!L25*'Бюджет '!$D$52 -> 1.2677349e+08 | ... AA78: ='План продаж'!S25*'Бюджет '!$D$52 -> 1.825206e+08 | AB78: ='План продаж'!AA25*'Бюджет '!$D$52 -> 1.8625304e+08 | AC78: ='План продаж'!AB25*'Бюджет '!$D$52 -> 1.7100433e+08 | AD78: ='План продаж'!AC25*'Бюджет '!$D$52 -> 1.7566913e+08 | AE78: ='План продаж'!AD25*'Бюджет '!$D$52 -> 1.8655024e+08 | AF78: ='План продаж'!AE25*'Бюджет '!$D$52 -> 1.3373054e+08 | AG78: ='План продаж'!AF25*'Бюджет '!$D$52 -> 1.0755718e+08 | AH78: ='План продаж'!AG25*'Бюджет '!$D$52 -> 37709052 | AI78: ='План продаж'!AH25*'Бюджет '!$D$52 -> 6600814.7 | ... AS78: ='План продаж'!AR25*'Бюджет '!$D$52 -> 0
A79: Реклама | B79: ='Бюджет '!F51 -> 4.1948092e+09 | C79: =SUM(G79:AS79) -> 4.1345601e+09 | M79: ='Бюджет '!$D$51*'План продаж'!E25 -> 1.4645387e+08 | N79: ='Бюджет '!$D$51*'План продаж'!F25 -> 46460363 | O79: ='Бюджет '!$D$51*'План продаж'!G25 -> 31878224 | P79: ='Бюджет '!$D$51*'План продаж'!H25 -> 40102075 | Q79: ='Бюджет '!$D$51*'План продаж'!I25 -> 33828084 | R79: ='Бюджет '!$D$51*'План продаж'!J25 -> 87728393 | S79: ='Бюджет '!$D$51*'План продаж'!K25 -> 1.0439678e+08 | T79: ='Бюджет '!$D$51*'План продаж'!L25 -> 1.2677349e+08 | ... AS79: ='Бюджет '!$D$51*'План продаж'!AK25 -> 0
A81: НАЛОГИ | B81: =B84+B85+B86 -> 6.7450962e+09 | C81: =C84+C85+C86 -> 6.7450962e+09 | F81: =F84+F85+F86 -> 402407.42 | G81: =G84+G85+G86 -> 402407.42 | H81: =H84+H85+H86 -> 402407.42 | I81: =I84+I85+I86 -> 402407.42 | J81: =J84+J85+J86 -> 402407.42 | K81: =K84+K85+K86 -> 402407.42 | L81: =L84+L85+L86 -> 402407.42 | M81: =M84+M85+M86 -> 5402407.4 | ... Z81: =Z84+Z85+Z86 -> 5402407.4 | AA81: =AA84+AB85+AB86 -> 6.6588288e+09 | AB81: =AB84+AC85+AC86 -> 402407.42 | AC81: =AC84+AC85+AC86 -> 402407.42 | AD81: =AD84+AD85+AD86 -> 402407.42 | AE81: =AE84+AE85+AE86 -> 402407.42 | AF81: =AF84+AF85+AF86 -> 402407.42 | AG81: =AG84+AG85+AG86 -> 402407.42 | AH81: =AH84+AH85+AH86 -> 402407.42 | AI81: =AI84+AI85+AI86 -> 0 | AJ81: =AJ84+AJ85+AJ86 -> 0 | ... AS81: =AS84+AS85+AS86 -> 0
A84: Налог на имущество | B84: =D84*ТЭПы!C13 -> 11669815 | C84: =SUM(E84:AS84) -> 11669815 | D84: 0.002 | F84: =$B$84/7.25/4 -> 402407.42 | G84: =$B$84/7.25/4 -> 402407.42 | H84: =$B$84/7.25/4 -> 402407.42 | I84: =$B$84/7.25/4 -> 402407.42 | J84: =$B$84/7.25/4 -> 402407.42 | K84: =$B$84/7.25/4 -> 402407.42 | L84: =$B$84/7.25/4 -> 402407.42 | M84: =$B$84/7.25/4 -> 402407.42 | ... AH84: =$B$84/7.25/4 -> 402407.42
A85: НДС | B85: ='Бюджет '!F54 -> 0 | C85: =SUM(F85:AS85) -> 0 | D85: 0.22 | M85: 5000000 | N85: 5000000 | O85: 5000000 | P85: 5000000 | Q85: 5000000 | R85: 5000000 | S85: 5000000 | T85: 5000000 | U85: 5000000 | V85: 5000000 | W85: 5000000 | X85: 5000000 | Y85: 5000000 | Z85: 5000000 | AA85: 5000000 | AB85: =B85-SUM(F85:AA85) -> -75000000
A86: Налог на прибыль | B86: ='Бюджет '!F55 -> 6.7334264e+09 | C86: =SUM(F86:AS86) -> 6.7334264e+09 | D86: 0.25 | AB86: =B86 -> 6.7334264e+09
A88: КРЕДИТ
A90: Поступления | C90: =SUM(F90:AS90) -> 8.8986277e+10 | F90: =-F93+F95 -> 0 | G90: =-G93+G95 -> 0 | H90: =-H93+H95 -> 0 | I90: =-I93+I95 -> 0 | J90: =-J93+J95 -> 0 | K90: =-K93+K95 -> 0 | L90: =-L93+L95 -> 0 | M90: =-M93+M95 -> 0 | ... AS90: =-AS93+AS95 -> 0
A91: Остаток на эскроу BoP | C91: =MAX(F91:AS91) -> 8.8986277e+10 | F91: =E94 -> 0 | G91: =F94 -> 4.1843962e+09 | H91: =G94 -> 5.5118351e+09 | I91: =H94 -> 6.4226415e+09 | J91: =I94 -> 7.5684151e+09 | K91: =J94 -> 8.5349318e+09 | L91: =K94 -> 1.1041457e+10 | M91: =L94 -> 1.4024222e+10 | ... AS91: =AR94 -> 0
A92: Пополнение эскроу за вычетом ФОР | C92: =SUM(F92:AS92) -> 8.8986277e+10 | D92: 0 | F92: =F15*(1-$D$92)*F$8 -> 4.1843962e+09 | G92: =G15*(1-$D$92)*G$8 -> 1.3274389e+09 | H92: =H15*(1-$D$92)*H$8 -> 9.108064e+08 | I92: =I15*(1-$D$92)*I$8 -> 1.1457736e+09 | J92: =J15*(1-$D$92)*J$8 -> 9.665167e+08 | K92: =K15*(1-$D$92)*K$8 -> 2.5065255e+09 | L92: =L15*(1-$D$92)*L$8 -> 2.9827652e+09 | M92: =M15*(1-$D$92)*M$8 -> 3.6220998e+09 | ... AS92: =AS15*(1-$D$92)*AS$8 -> 0
A93: Раскрытие эскроу | C93: =SUM(F93:AS93) -> -8.8986277e+10 | F93: =-F6*SUM(F91,F92) -> 0 | G93: =-G6*SUM(G91,G92) -> 0 | H93: =-H6*SUM(H91,H92) -> 0 | I93: =-I6*SUM(I91,I92) -> 0 | J93: =-J6*SUM(J91,J92) -> 0 | K93: =-K6*SUM(K91,K92) -> 0 | L93: =-L6*SUM(L91,L92) -> 0 | M93: =-M6*SUM(M91,M92) -> 0 | ... AS93: =-AS6*SUM(AS91,AS92) -> 0 | AT93: где еще 5%
A94: Остаток на эскроу EoP | C94: =MAX(F94:AS94) -> 8.8986277e+10 | F94: =SUM(F91:F93) -> 4.1843962e+09 | G94: =SUM(G91:G93) -> 5.5118351e+09 | H94: =SUM(H91:H93) -> 6.4226415e+09 | I94: =SUM(I91:I93) -> 7.5684151e+09 | J94: =SUM(J91:J93) -> 8.5349318e+09 | K94: =SUM(K91:K93) -> 1.1041457e+10 | L94: =SUM(L91:L93) -> 1.4024222e+10 | M94: =SUM(M91:M93) -> 1.7646322e+10 | ... AS94: =SUM(AS91:AS93) -> 0
A95: Продажи по ДКП | C95: =SUM(F95:AS95) -> 0 | F95: =F15*F9 -> 0 | G95: =G15*G9 -> 0 | H95: =H15*H9 -> 0 | I95: =I15*I9 -> 0 | J95: =J15*J9 -> 0 | K95: =K15*K9 -> 0 | L95: =L15*L9 -> 0 | M95: =M15*M9 -> 0 | ... AS95: =AS15*AS9 -> 0
A97: Total Debt (BoP) | C97: =MAX(F97:AS97) -> 0 | G97: =F106 -> 0 | H97: =G106 -> 0 | I97: =H106 -> 0 | J97: =I106 -> 0 | K97: =J106 -> 0 | L97: =K106 -> 0 | M97: =L106 -> 0 | N97: =M106 -> 0 | ... AS97: =AR106 -> 0
A98: Выборка | C98: =SUM(F98:AS98) -> -8.1180073e+10 | F98: =-SUM(F18,F132)*F8 -> -2.8585425e+09 | G98: =-SUM(G18,G132)*G8 -> -7.5809277e+08 | H98: =-SUM(H18,H132)*H8 -> -1.9133033e+09 | I98: =-SUM(I18,I132)*I8 -> -1.9475713e+09 | J98: =-SUM(J18,J132)*J8 -> -1.9475713e+09 | K98: =-SUM(K18,K132)*K8 -> -3.4839979e+09 | L98: =-SUM(L18,L132)*L8 -> -2.5749065e+09 | M98: =-SUM(M18,M132)*M8 -> -3.9688534e+09 | ... AS98: =-SUM(AS18,AS132)*AS8 -> 0
A99: Погашение | C99: =SUM(F99:AS99) -> 8.1180073e+10 | F99: =SUM(F100,F101) -> 2.8585425e+09 | G99: =SUM(G100,G101) -> 7.5809277e+08 | H99: =SUM(H100,H101) -> 1.9133033e+09 | I99: =SUM(I100,I101) -> 1.9475713e+09 | J99: =SUM(J100,J101) -> 1.9475713e+09 | K99: =SUM(K100,K101) -> 3.4839979e+09 | L99: =SUM(L100,L101) -> 2.5749065e+09 | M99: =SUM(M100,M101) -> 3.9688534e+09 | ... AS99: =SUM(AS100,AS101) -> 0
A100: в т.ч. за счёт эскроу | C100: =SUM(F100:AS100) -> 8.1180073e+10 | F100: =MAX(F93/(1-$D$92)+F108,-F97-F98) -> 2.8585425e+09 | G100: =MAX(G93/(1-$D$92)+G108,-G97-G98) -> 7.5809277e+08 | H100: =MAX(H93/(1-$D$92)+H108,-H97-H98) -> 1.9133033e+09 | I100: =MAX(I93/(1-$D$92)+I108,-I97-I98) -> 1.9475713e+09 | J100: =MAX(J93/(1-$D$92)+J108,-J97-J98) -> 1.9475713e+09 | K100: =MAX(K93/(1-$D$92)+K108,-K97-K98) -> 3.4839979e+09 | L100: =MAX(L93/(1-$D$92)+L108,-L97-L98) -> 2.5749065e+09 | M100: =MAX(M93/(1-$D$92)+M108,-M97-M98) -> 3.9688534e+09 | ... AS100: =MAX(AS93/(1-$D$92)+AS108,-AS97-AS98) -> 0
A101: в т.ч. за счёт ДКП | C101: =SUM(F101:AS101) -> 0 | F101: =M105 -> 0 | G101: =N105 -> 0 | H101: =O105 -> 0 | I101: =P105 -> 0 | J101: =Q105 -> 0 | K101: =R105 -> 0 | L101: =S105 -> 0 | M101: =T105 -> 0 | ... AS101: =AZ105 -> 0
A102: Определение залоговой стоимости квартир | D102: 0.15 | K102: ='План продаж'!E58*(1-$D$102) -> 423047.55 | L102: ='План продаж'!F58*(1-$D$102) -> 431508.5 | M102: ='План продаж'!G58*(1-$D$102) -> 440138.67 | N102: ='План продаж'!H58*(1-$D$102) -> 448941.44 | O102: ='План продаж'!I58*(1-$D$102) -> 457920.27 | P102: ='План продаж'!J58*(1-$D$102) -> 467078.68 | Q102: ='План продаж'!K58*(1-$D$102) -> 476420.25 | R102: ='План продаж'!L58*(1-$D$102) -> 485948.66 | ... AT102: ='План продаж'!AN58*(1-$D$102) -> 0
A103: Задолженность после раскрытия escrow | F103: =E$106*E$8*F$9 -> 0 | G103: =F$106*F$8*G$9 -> 0 | H103: =G$106*G$8*H$9 -> 0 | I103: =H$106*H$8*I$9 -> 0 | J103: =I$106*I$8*J$9 -> 0 | K103: =J$106*J$8*K$9 -> 0 | L103: =K$106*K$8*L$9 -> 0 | M103: =L$106*L$8*M$9 -> 0 | ... AS103: =AR$106*AR$8*AS$9 -> 0
A104: Остаток площадей после раскрытия escrow | I104: =H$8*I$9*SUM('План продаж'!A59:AI59) -> 0 | J104: =I$8*J$9*SUM('План продаж'!B59:AJ59) -> 0 | K104: =J$8*K$9*SUM('План продаж'!C59:AK59) -> 0 | L104: =K$8*L$9*SUM('План продаж'!D59:AL59) -> 0 | M104: =L$8*M$9*SUM('План продаж'!E59:AM59) -> 0 | N104: =M$8*N$9*SUM('План продаж'!F59:AN59) -> 0 | O104: =N$8*O$9*SUM('План продаж'!G59:AO59) -> 0 | P104: =O$8*P$9*SUM('План продаж'!H59:AP59) -> 0 | ... AS104: =AR$8*AS$9*SUM('План продаж'!AK59:BS59) -> 0
A105: Погашение по залог. стоимости (квартиры) | M105: =-MIN('План продаж'!E59:S59)*F9 -> 0 | N105: =-MIN('План продаж'!F59:T59)*G9 -> 0 | O105: =-MIN('План продаж'!G59:U59)*H9 -> 0 | P105: =-MIN('План продаж'!H59:V59)*I9 -> 0 | Q105: =-MIN('План продаж'!I59:W59)*J9 -> 0 | R105: =-MIN('План продаж'!J59:X59)*K9 -> 0 | S105: =-MIN('План продаж'!K59:Y59)*L9 -> 0 | T105: =-MIN('План продаж'!L59:Z59)*M9 -> 0 | ... AS105: =-MIN('План продаж'!AK59:AY59)*AL9 -> 0
A106: Total Debt (EoP) | F106: =F97+F98+F99 -> 0 | G106: =G97+G98+G99 -> 0 | H106: =H97+H98+H99 -> 0 | I106: =I97+I98+I99 -> 0 | J106: =J97+J98+J99 -> 0 | K106: =K97+K98+K99 -> 0 | L106: =L97+L98+L99 -> 0 | M106: =M97+M98+M99 -> 0 | ... AS106: =AS97+AS98+AS99 -> 0
A107: Проценты начисленные | C107: =SUM(F107:AS107) -> -1.4386244e+10 | F107: =(AVERAGE(F97,F97+F98)+E107)*F125*F3/365 -> -1.4096922e+08 | G107: =(AVERAGE(G97,G97+G98)+F107)*G125*G3/365 -> -6.031805e+08 | H107: =(AVERAGE(H97,H97+H98)+G107)*H125*H3/365 -> -4.6284977e+08 | I107: =(AVERAGE(I97,I97+I98)+H107)*I125*I3/365 -> -3.4095605e+08 | J107: =(AVERAGE(J97,J97+J98)+I107)*J125*J3/365 -> -2.8459392e+08 | K107: =(AVERAGE(K97,K97+K98)+J107)*K125*K3/365 -> -4.3404629e+08 | L107: =(AVERAGE(L97,L97+L98)+K107)*L125*L3/365 -> -3.6785708e+08 | M107: =(AVERAGE(M97,M97+M98)+L107)*M125*M3/365 -> -5.4167306e+08 | ... AS107: =(AVERAGE(AS97,AS97+AS98)+AR107)*AS125*AS3/365 -> -6.7399126e-15
A108: Проценты (PIK), оплата при раскрытии escrow | C108: =SUM(F108:AS108) -> -1.4381644e+10 | F108: =SUM($F$107:F107)*IF(F93<0,1,0) -> 0 | G108: =SUM($F$107:G107)*IF(G93<0,1,0) -> 0 | H108: =SUM($F$107:H107)*IF(H93<0,1,0) -> 0 | I108: =SUM($F$107:I107)*IF(I93<0,1,0) -> 0 | J108: =SUM($F$107:J107)*IF(J93<0,1,0) -> 0 | K108: =SUM($F$107:K107)*IF(K93<0,1,0) -> 0 | L108: =SUM($F$107:L107)*IF(L93<0,1,0) -> 0 | M108: =SUM($F$107:M107)*IF(M93<0,1,0) -> 0 | ... AS108: =SUM($F$107:AS107)*IF(AS93<0,1,0) -> 0
A109: Проценты (PIK), оплата из ДКП | C109: =SUM(F109:AS109) -> 0 | F109: =MIN(MAX(-F93*(1+$D$92)+F95+F18+F84+F85,0),(SUM($E$107:F107)-SUM($E$108:F108)-SUM($E$109:E109)))*F9 -> 0 | G109: =MIN(MAX(-G93*(1+$D$92)+G95+G18+G84+G85,0),(SUM($E$107:G107)-SUM($E$108:G108)-SUM($E$109:F109)))*G9 -> 0 | H109: =MIN(MAX(-H93*(1+$D$92)+H95+H18+H84+H85,0),(SUM($E$107:H107)-SUM($E$108:H108)-SUM($E$109:G109)))*H9 -> 0 | I109: =MIN(MAX(-I93*(1+$D$92)+I95+I18+I84+I85,0),(SUM($E$107:I107)-SUM($E$108:I108)-SUM($E$109:H109)))*I9 -> 0 | J109: =MIN(MAX(-J93*(1+$D$92)+J95+J18+J84+J85,0),(SUM($E$107:J107)-SUM($E$108:J108)-SUM($E$109:I109)))*J9 -> 0 | K109: =MIN(MAX(-K93*(1+$D$92)+K95+K18+K84+K85,0),(SUM($E$107:K107)-SUM($E$108:K108)-SUM($E$109:J109)))*K9 -> 0 | L109: =MIN(MAX(-L93*(1+$D$92)+L95+L18+L84+L85,0),(SUM($E$107:L107)-SUM($E$108:L108)-SUM($E$109:K109)))*L9 -> 0 | M109: =MIN(MAX(-M93*(1+$D$92)+M95+M18+M84+M85,0),(SUM($E$107:M107)-SUM($E$108:M108)-SUM($E$109:L109)))*M9 -> 0 | ... Z109: =MIN(MAX(-Z93*(1+$D$92)+Z95+Z18+Z84+Z85,0),(SUM($E$107:Z107)-SUM($E$108:Z108)-SUM($E$109:Y109)))*Z9 -> 0 | AA109: =MIN(MAX(-AA93*(1+$D$92)+AA95+AA18+AA84+AB85,0),(SUM($E$107:AA107)-SUM($E$108:AA108)-SUM($E$109:Z109)))*AA9 -> 0 | AB109: =MIN(MAX(-AB93*(1+$D$92)+AB95+AB18+AB84+AC85,0),(SUM($E$107:AB107)-SUM($E$108:AB108)-SUM($E$109:AA109)))*AB9 -> 0 | AC109: =MIN(MAX(-AC93*(1+$D$92)+AC95+AC18+AC84+AC85,0),(SUM($E$107:AC107)-SUM($E$108:AC108)-SUM($E$109:AB109)))*AC9 -> 0 | AD109: =MIN(MAX(-AD93*(1+$D$92)+AD95+AD18+AD84+AD85,0),(SUM($E$107:AD107)-SUM($E$108:AD108)-SUM($E$109:AC109)))*AD9 -> 0 | AE109: =MIN(MAX(-AE93*(1+$D$92)+AE95+AE18+AE84+AE85,0),(SUM($E$107:AE107)-SUM($E$108:AE108)-SUM($E$109:AD109)))*AE9 -> 0 | AF109: =MIN(MAX(-AF93*(1+$D$92)+AF95+AF18+AF84+AF85,0),(SUM($E$107:AF107)-SUM($E$108:AF108)-SUM($E$109:AE109)))*AF9 -> 0 | AG109: =MIN(MAX(-AG93*(1+$D$92)+AG95+AG18+AG84+AG85,0),(SUM($E$107:AG107)-SUM($E$108:AG108)-SUM($E$109:AF109)))*AG9 -> 0 | AH109: =MIN(MAX(-AH93*(1+$D$92)+AH95+AH18+AH84+AH85,0),(SUM($E$107:AH107)-SUM($E$108:AH108)-SUM($E$109:AG109)))*AH9 -> 0 | AI109: =MIN(MAX(-AI93*(1+$D$92)+AI95+AI18+AI84+AI85,0),(SUM($E$107:AI107)-SUM($E$108:AI108)-SUM($E$109:AH109)))*AI9 -> 0 | AJ109: =MIN(MAX(-AJ93*(1+$D$92)+AJ95+AJ18+AJ84+AJ85,0),(SUM($E$107:AJ107)-SUM($E$108:AJ108)-SUM($E$109:AI109)))*AJ9 -> 0 | ... AS109: =MIN(MAX(-AS93*(1+$D$92)+AS95+AS18+AS84+AS85,0),(SUM($E$107:AS107)-SUM($E$108:AS108)-SUM($E$109:AR109)))*AS9 -> 0
A110: НеупПр (EoP) | C110: =MAX(F110:AS110) -> 0 | F110: =E110+F107-F108-F109 -> -1.4096922e+08 | G110: =F110+G107-G108-G109 -> -7.4414972e+08 | H110: =G110+H107-H108-H109 -> -1.2069995e+09 | I110: =H110+I107-I108-I109 -> -1.5479555e+09 | J110: =I110+J107-J108-J109 -> -1.8325495e+09 | K110: =J110+K107-K108-K109 -> -2.2665957e+09 | L110: =K110+L107-L108-L109 -> -2.6344528e+09 | M110: =L110+M107-M108-M109 -> -3.1761259e+09 | ... AS110: =AR110+AS107-AS108-AS109 -> -4600843.4
...

Sheet План продаж
D1: =SUM(E1:AG1) -> 961 | E1: 57 | F1: 18 | G1: 11 | H1: 14 | I1: =I22*$D$8 -> 12 | J1: 30 | K1: 36 | L1: =L22*$D$8 -> 40 | M1: =M22*$D$8 -> 42 | N1: 35 | O1: 41 | P1: 45 | Q1: 46 | R1: 47 | S1: 47 | T1: =T22*$D$8 -> 46 | U1: =U22*$D$8 -> 46 | V1: 44 | W1: 43 | X1: 41 | Y1: =Y22*$D$8 -> 34 | Z1: =Z22*$D$8 -> 34 | AA1: 30 | AB1: 27 | AC1: 27 | AD1: 27 | AE1: 19 | AF1: 17 | AG1: 5
D2: =SUM(E2:AG2) -> 720 | E2: 42 | F2: 13 | G2: 9 | H2: 11 | I2: =I22*$D$9 -> 9 | J2: 23 | K2: 26 | L2: =L22*$D$9 -> 30 | M2: 32 | N2: 26 | O2: 31 | P2: 35 | Q2: 35 | R2: 35 | S2: 33 | T2: 34 | U2: 34 | V2: 33 | W2: 33 | X2: 31 | Y2: 25 | Z2: 25 | AA2: 22 | AB2: 21 | AC2: 21 | AD2: 21 | AE2: 14 | AF2: 12 | AG2: 4
D3: =SUM(E3:AG3) -> 720 | E3: 42 | F3: 13 | G3: 9 | H3: 11 | I3: =I22*$D$10 -> 9 | J3: 23 | K3: 27 | L3: =L22*$D$10 -> 30 | M3: 31 | N3: 27 | O3: 31 | P3: 31 | Q3: 34 | R3: 36 | S3: 33 | T3: 35 | U3: 35 | V3: 34 | W3: 33 | X3: 31 | Y3: 25 | Z3: 25 | AA3: 22 | AB3: 21 | AC3: 21 | AD3: 21 | AE3: 14 | AF3: 12 | AG3: 4
D4: =SUM(E4:AG4) -> 2401 | E4: =E1+E2+E3 -> 141 | F4: =F1+F2+F3 -> 44 | G4: =G1+G2+G3 -> 29 | H4: =H1+H2+H3 -> 36 | I4: =I1+I2+I3 -> 30 | J4: =J1+J2+J3 -> 76 | K4: =K1+K2+K3 -> 89 | L4: =L1+L2+L3 -> 100 | ... AG4: =AG1+AG2+AG3 -> 13
C5: =ТЭПы!B38 -> Квартирография - цены старта продаж
B7: =ТЭПы!A40 -> 0 | C7: =ТЭПы!B40 -> Типы квартир | D7: =ТЭПы!C40 -> 0 | E7: =ТЭПы!D40 -> S квартиры | F7: =ТЭПы!E40 -> S | G7: =ТЭПы!F40 -> кол-во | H7: =ТЭПы!G40 -> цена 1м2 | I7: =ТЭПы!H40 -> Средний чек | ... K7: =ТЭПы!J40 -> Машиноместа
B8: =ТЭПы!A41 -> 0 | C8: =ТЭПы!B41 -> Квартиры Тип 1 | D8: =ТЭПы!C41 -> 0.4 | E8: =ТЭПы!D41 -> 35.108 | F8: =ТЭПы!E41 -> 33738.788 | G8: =ТЭПы!F41 -> 961 | H8: =ТЭПы!G41 -> 497703 | I8: =ТЭПы!H41 -> 17473357 | ... K8: =ТЭПы!J41 -> 768.8 | L8: =G8*E8 -> 33738.788
B9: =ТЭПы!A42 -> 0 | C9: =ТЭПы!B42 -> Квартиры Тип 2 | D9: =ТЭПы!C42 -> 0.3 | E9: =ТЭПы!D42 -> 60.53 | F9: =ТЭПы!E42 -> 43581.6 | G9: =ТЭПы!F42 -> 720 | H9: =ТЭПы!G42 -> 497703 | I9: =ТЭПы!H42 -> 30125963 | ... K9: =ТЭПы!J42 -> 864
B10: =ТЭПы!A43 -> 0 | C10: =ТЭПы!B43 -> Квартиры Тип 3 | D10: =ТЭПы!C43 -> 0.3 | E10: =ТЭПы!D43 -> 92 | F10: =ТЭПы!E43 -> 66240 | G10: =ТЭПы!F43 -> 720 | H10: =ТЭПы!G43 -> 497703 | I10: =ТЭПы!H43 -> 45788676 | ... K10: =ТЭПы!J43 -> 1152
B11: =ТЭПы!A44 -> 0 | C11: =ТЭПы!B44 -> 0 | D11: =ТЭПы!C44 -> 0 | E11: =ТЭПы!D44 -> 59.791915 | F11: =ТЭПы!E44 -> 143560.39 | G11: =ТЭПы!F44 -> 2401 | H11: =ТЭПы!G44 -> 497703 | I11: =ТЭПы!H44 -> 31129332 | ... K11: =ТЭПы!J44 -> 862
B14: =ТЭПы!A47 -> 0 | C14: =ТЭПы!B47 -> Типы прочих помещений | D14: =ТЭПы!C47 -> 0 | E14: =ТЭПы!D47 -> S коммерции | F14: =ТЭПы!E47 -> S | G14: =ТЭПы!F47 -> кол-во | H14: =ТЭПы!G47 -> цена 1м2 | I14: =ТЭПы!H47 -> Средний чек | ... K14: =ТЭПы!J47 -> 0
B15: =ТЭПы!A48 -> 0 | C15: =ТЭПы!B48 -> ПСН | D15: =ТЭПы!C48 -> 10332 | E15: =ТЭПы!D48 -> 80 | F15: =ТЭПы!E48 -> 10322 | G15: =ТЭПы!F48 -> 129.025 | H15: =ТЭПы!G48 -> 600000 | I15: =ТЭПы!H48 -> 48000000 | ... K15: =ТЭПы!J48 -> 0
B16: =ТЭПы!A49 -> 0 | C16: =ТЭПы!B49 -> Машиноместа | D16: =ТЭПы!C49 -> 5200 | E16: =ТЭПы!D49 -> 40.945 | F16: =ТЭПы!E49 -> 35294.59 | G16: =ТЭПы!F49 -> 862 | H16: =ТЭПы!G49 -> 270000 | I16: =ТЭПы!H49 -> 11055150 | ... K16: =ТЭПы!J49 -> 0
B17: =ТЭПы!A50 -> 0 | C17: =ТЭПы!B50 -> Прочие помещения | D17: =ТЭПы!C50 -> 0 | E17: =ТЭПы!D50 -> 0 | F17: =ТЭПы!E50 -> 0 | G17: =ТЭПы!F50 -> 0 | H17: =ТЭПы!G50 -> 0 | I17: =ТЭПы!H50 -> 0 | ... K17: =ТЭПы!J50 -> 0
B18: =ТЭПы!A51 -> 0 | C18: =ТЭПы!B51 -> 0 | D18: =ТЭПы!C51 -> 0 | E18: =ТЭПы!D51 -> 0 | F18: =ТЭПы!E51 -> 45616.59 | G18: =ТЭПы!F51 -> 991.025 | H18: =ТЭПы!G51 -> 435000 | I18: =ТЭПы!H51 -> 0 | ... K18: =ТЭПы!J51 -> 0
D21: =SUM(E21:AG21) -> 143560.33 | E21: 9314.2 | F21: 2888.2 | G21: 1900 | H21: 2400 | I21: 1970.6586 | J21: 4635.3318 | K21: 5297.1555 | L21: 5958.9792 | M21: 6199.6424 | N21: 5297.1555 | O21: 6197.1186 | P21: 6737.0965 | Q21: 6977.0867 | R21: 7097.0818 | S21: 6610.2089 | T21: 6910.1966 | U21: 6910.1966 | V21: 6529.3748 | W21: 6308.2159 | X21: 5994.0859 | Y21: 4808.2159 | Z21: 4808.2159 | AA21: 4206.558 | AB21: 3906.5702 | AC21: 3906.5702 | AD21: 3906.5702 | AE21: 2703.2544 | AF21: 2402.4254 | AG21: 779.96805
B22: =B28+B33+B38 -> 2401 | D22: =SUM(E22:AG22) -> 2401 | E22: 141 | F22: 44 | G22: 29 | H22: 36 | I22: 30 | J22: 76 | K22: 88 | L22: 100 | M22: 105 | N22: 88 | O22: 103 | P22: 112 | Q22: 116 | R22: 118 | S22: 111 | T22: 115 | U22: 115 | V22: 111 | W22: 108 | X22: 103 | Y22: 85 | Z22: 85 | AA22: 74 | AB22: 69 | AC22: 69 | AD22: 69 | AE22: 47 | AF22: 41 | AG22: 13
C23: 1 очередь | E23: РнС | AA23: РнВ | AG23: конец продаж
C24: Кол-во кварталов | E24: 1 квартал 26 | F24: 2 квартал 26 | G24: 3 квартал 26 | H24: 4 квартал 26 | I24: 1 квартал 27 | J24: 2 квартал 27 | K24: 3 квартал 27 | L24: 4 квартал 27 | M24: 1 квартал 28 | N24: 2 квартал 28 | O24: 3 квартал 28 | P24: 4 квартал 28 | Q24: 1 квартал 29 | R24: 2 квартал 29 | S24: 3 квартал 29 | T24: 4 квартал 29 | U24: 1 квартал 30 | V24: 2 квартал 30 | W24: 3 квартал 30 | X24: 4 квартал 30 | Y24: 1 квартал 31 | Z24: 2 квартал 31 | AA24: 3 квартал 31 | AB24: 4 квартал 31 | AC24: 1 квартал 32 | AD24: 2 квартал 32 | AE24: 3 квартал 32 | AF24: 4 квартал 32 | AG24: 1 кварлал 2033 | AH24: 17 кварлал 2031 | AI24: 18 кварлал 2031 | AJ24: 19 кварлал 2031 | AK24: 20 кварлал 2031 | AL24: 21 кварлал 2031 | AM24: 22 кварлал 2031
C25: ИТОГО сделки с индекс | D25: =D27+D32+D37+D42+D52+D47 -> 1.1813029e+11 | E25: =E27+E32+E37+E42+E52+E47 -> 4.1843962e+09 | F25: =F27+F32+F37+F42+F52+F47 -> 1.3274389e+09 | G25: =G27+G32+G37+G42+G52+G47 -> 9.108064e+08 | H25: =H27+H32+H37+H42+H52+H47 -> 1.1457736e+09 | I25: =I27+I32+I37+I42+I52+I47 -> 9.665167e+08 | J25: =J27+J32+J37+J42+J52+J47 -> 2.5065255e+09 | K25: =K27+K32+K37+K42+K52+K47 -> 2.9827652e+09 | ... AM25: =AM27+AM32+AM37+AM42+AM52+AM47 -> 0
C26: ИТОГО ПЛОЩАДЬ | D26: =D29+D34+D39+D44 -> 116852.05 | E26: =E29+E34+E39+E44+E54+E49 -> 8407.416 | F26: =F29+F34+F39+F44+F54+F49 -> 2614.834 | G26: =G29+G34+G39+G44+G54+G49 -> 1758.958 | H26: =H29+H34+H39+H44+H54+H49 -> 2169.342 | I26: =I29+I34+I39+I44+I54+I49 -> 1794.066 | J26: =J29+J34+J39+J44+J54+J49 -> 4561.43 | K26: =K29+K34+K39+K44+K54+K49 -> 5321.668 | L26: =L29+L34+L39+L44+L54+L49 -> 6635.34 | ... AM26: =AM29+AM34+AM39+AM44+AM54+AM49 -> 0
B27: =E8 -> 35.108 | C27: =C8 -> Квартиры Тип 1 | D27: =SUM(E27:AU27) -> 2.2164067e+10 | E27: =E31*E29 -> 9.9598134e+08 | F27: =F31*F29 -> 3.2081083e+08 | G27: =G31*G29 -> 1.9997209e+08 | H27: =H31*H29 -> 2.5960013e+08 | I27: =I31*I29 -> 2.2696468e+08 | J27: =J31*J29 -> 5.7875994e+08 | K27: =K31*K29 -> 7.0840216e+08 | L27: =L31*L29 -> 8.0285579e+08 | ... AM27: =AM31*AM29 -> 0
B28: =G8 -> 961 | C28: Темп продаж, шт | D28: =SUM(E28:AU28) -> 961 | E28: 57 | F28: 18 | G28: 11 | H28: 14 | I28: 12 | J28: 30 | K28: 36 | L28: 40 | M28: 42 | N28: 35 | O28: 41 | P28: 45 | Q28: 46 | R28: 47 | S28: 47 | T28: 46 | U28: 46 | V28: 44 | W28: 43 | X28: 41 | Y28: 34 | Z28: 34 | AA28: 30 | AB28: 27 | AC28: 27 | AD28: 27 | AE28: 19 | AF28: 17 | AG28: 5
B29: =F8 -> 33738.788 | C29: Темп продаж, кв. м | D29: =SUM(E29:AM29) -> 33738.788 | E29: =E28*$B$27 -> 2001.156 | F29: =F28*$B$27 -> 631.944 | G29: =G28*$B$27 -> 386.188 | H29: =H28*$B$27 -> 491.512 | I29: =I28*$B$27 -> 421.296 | J29: =J28*$B$27 -> 1053.24 | K29: =K28*$B$27 -> 1263.888 | L29: =L28*$B$27 -> 1404.32 | ... AM29: =AM28*$B$27 -> 0
C30: Рост цен (от стадии проекта),% | D30: =SUM(E30:T30) -> 0.32 | E30: 0.02 | F30: =E30 -> 0.02 | G30: =F30 -> 0.02 | H30: =G30 -> 0.02 | I30: =H30 -> 0.02 | J30: =I30 -> 0.02 | K30: =J30 -> 0.02 | L30: =K30 -> 0.02 | M30: =L30 -> 0.02 | ... AM30: =AL30 -> 0.02
B31: =H8 -> 497703 | C31: Цена продаж, тыс.руб./кв.м | D31: =AVERAGE(E31:S31) -> 573799.03 | E31: =B31 -> 497703 | F31: =E31+E31*E30 -> 507657.06 | G31: =F31+F31*F30 -> 517810.2 | H31: =G31+G31*G30 -> 528166.41 | I31: =H31+H31*H30 -> 538729.73 | J31: =I31+I31*I30 -> 549504.33 | K31: =J31+J31*J30 -> 560494.41 | L31: =K31+K31*K30 -> 571704.3 | M31: =L31+L31*L30 -> 583138.39 | ... AM31: =AL31+AL31*AL30 -> 975834.34
B32: =E9 -> 60.53 | C32: =C9 -> Квартиры Тип 2 | D32: =SUM(E32:AU32) -> 2.8633526e+10 | E32: =E36*E34 -> 1.2652904e+09 | F32: =F36*F34 -> 3.9947026e+08 | G32: =G36*G34 -> 2.8208746e+08 | H32: =H36*H34 -> 3.5166904e+08 | I32: =I36*I34 -> 2.934838e+08 | J32: =J36*J34 -> 7.6501443e+08 | K32: =K36*K34 -> 8.820949e+08 | L32: =L36*L34 -> 1.0381578e+09 | ... AM32: =AM36*AM34 -> 0
B33: =G9 -> 720 | C33: Темп продаж, шт | D33: =SUM(E33:AU33) -> 720 | E33: 42 | F33: 13 | G33: 9 | H33: 11 | I33: 9 | J33: 23 | K33: 26 | L33: 30 | M33: 32 | N33: 26 | O33: 31 | P33: 35 | Q33: 35 | R33: 35 | S33: 33 | T33: 34 | U33: 34 | V33: 33 | W33: 33 | X33: 31 | Y33: 25 | Z33: 25 | AA33: 22 | AB33: 21 | AC33: 21 | AD33: 21 | AE33: 14 | AF33: 12 | AG33: 4
B34: =F9 -> 43581.6 | C34: Темп продаж, кв. м | D34: =SUM(E34:Z34) -> 36620.65 | E34: =E33*$B$32 -> 2542.26 | F34: =F33*$B$32 -> 786.89 | G34: =G33*$B$32 -> 544.77 | H34: =H33*$B$32 -> 665.83 | I34: =I33*$B$32 -> 544.77 | J34: =J33*$B$32 -> 1392.19 | K34: =K33*$B$32 -> 1573.78 | L34: =L33*$B$32 -> 1815.9 | ... AM34: =AM33*$B$32 -> 0
C35: Рост цен (от стадии проекта),% | D35: =SUM(E35:T35) -> 0.32 | E35: 0.02 | F35: =E35 -> 0.02 | G35: =F35 -> 0.02 | H35: =G35 -> 0.02 | I35: =H35 -> 0.02 | J35: =I35 -> 0.02 | K35: =J35 -> 0.02 | L35: =K35 -> 0.02 | M35: =L35 -> 0.02 | ... AM35: =AL35 -> 0.02
B36: =H9 -> 497703 | C36: Цена продаж, тыс.руб./кв.м | D36: =AVERAGE(E36:S36) -> 573799.03 | E36: =B36 -> 497703 | F36: =E36+E36*E35 -> 507657.06 | G36: =F36+F36*F35 -> 517810.2 | H36: =G36+G36*G35 -> 528166.41 | I36: =H36+H36*H35 -> 538729.73 | J36: =I36+I36*I35 -> 549504.33 | K36: =J36+J36*J35 -> 560494.41 | L36: =K36+K36*K35 -> 571704.3 | M36: =L36+L36*L35 -> 583138.39 | ... AM36: =AL36+AL36*AL35 -> 975834.34
B37: =E10 -> 92 | C37: =C10 -> Квартиры Тип 3 | D37: =SUM(E37:AU37) -> 4.3534979e+10 | E37: =E41*E39 -> 1923124392 | F37: =F41*F39 -> 6.0715784e+08 | G37: =G41*G39 -> 4.2874685e+08 | H37: =H41*H39 -> 5.345044e+08 | I37: =I41*I39 -> 4.4606822e+08 | J37: =J41*J39 -> 1.1627512e+09 | K37: =K41*K39 -> 1.3922681e+09 | L37: =L41*L39 -> 1.5779039e+09 | ... AM37: =AM41*AM39 -> 0
B38: =G10 -> 720 | C38: Темп продаж, шт | D38: =SUM(E38:AU38) -> 720 | E38: 42 | F38: 13 | G38: 9 | H38: 11 | I38: 9 | J38: 23 | K38: 27 | L38: 30 | M38: 31 | N38: 27 | O38: 31 | P38: 31 | Q38: 34 | R38: 36 | S38: 33 | T38: 35 | U38: 35 | V38: 34 | W38: 33 | X38: 31 | Y38: 25 | Z38: 25 | AA38: 22 | AB38: 21 | AC38: 21 | AD38: 21 | AE38: 14 | AF38: 12 | AG38: 4
B39: =F10 -> 66240 | C39: Темп продаж, кв. м | D39: =SUM(E39:S39) -> 35604 | E39: =E38*$B$37 -> 3864 | F39: =F38*$B$37 -> 1196 | G39: =G38*$B$37 -> 828 | H39: =H38*$B$37 -> 1012 | I39: =I38*$B$37 -> 828 | J39: =J38*$B$37 -> 2116 | K39: =K38*$B$37 -> 2484 | L39: =L38*$B$37 -> 2760 | ... AM39: =AM38*$B$37 -> 0
C40: Рост цен (от стадии проекта),% | D40: =SUM(E40:T40) -> 0.32 | E40: 0.02 | F40: =E40 -> 0.02 | G40: =F40 -> 0.02 | H40: =G40 -> 0.02 | I40: =H40 -> 0.02 | J40: =I40 -> 0.02 | K40: =J40 -> 0.02 | L40: =K40 -> 0.02 | M40: =L40 -> 0.02 | ... AM40: =AL40 -> 0.02
B41: =H10 -> 497703 | C41: Цена продаж, тыс.руб./кв.м | D41: =AVERAGE(E41:S41) -> 573799.03 | E41: =B41 -> 497703 | F41: =E41+E41*E40 -> 507657.06 | G41: =F41+F41*F40 -> 517810.2 | H41: =G41+G41*G40 -> 528166.41 | I41: =H41+H41*H40 -> 538729.73 | J41: =I41+I41*I40 -> 549504.33 | K41: =J41+J41*J40 -> 560494.41 | L41: =K41+K41*K40 -> 571704.3 | M41: =L41+L41*L40 -> 583138.39 | ... AM41: =AL41+AL41*AL40 -> 975834.34
B42: =E15 -> 80 | C42: =C15 -> ПСН | D42: =SUM(E42:AU42) -> 1.0206468e+10 | E42: =E46*E44 -> 0 | F42: =F46*F44 -> 0 | G42: =G46*G44 -> 0 | H42: =H46*H44 -> 0 | I42: =I46*I44 -> 0 | J42: =J46*J44 -> 0 | K42: =K46*K44 -> 0 | L42: =L46*L44 -> 0 | ... AM42: =AM46*AM44 -> 0
B43: =G15 -> 129.025 | C43: Темп продаж, шт | D43: =SUM(E43:AU43) -> 136.1076 | E43: 0 | F43: 0 | G43: 0 | H43: 0 | I43: 0 | J43: 0 | K43: 0 | L43: 0 | M43: 0 | N43: 0 | O43: 0 | P43: 0 | Q43: 0 | R43: 2.2125 | S43: 2.2125 | T43: 2.6525 | U43: 5 | V43: 5 | W43: 5 | X43: 7.6775 | Y43: 11.1425 | Z43: 8.62875 | AA43: 16.55375 | AB43: 13.6775 | AC43: 13.6775 | AD43: 15.89 | AE43: 9.5276 | AF43: 7.965 | AG43: 2.2125 | AH43: 2.2125 | AI43: 2.2125 | AJ43: 2.6525 | AK43: 0 | AL43: 0 | AM43: 0
B44: =F15 -> 10322 | C44: Темп продаж, кв. м | D44: =SUM(E44:AU44) -> 10888.608 | E44: =E43*$B$42 -> 0 | F44: =F43*$B$42 -> 0 | G44: =G43*$B$42 -> 0 | H44: =H43*$B$42 -> 0 | I44: =I43*$B$42 -> 0 | J44: =J43*$B$42 -> 0 | K44: =K43*$B$42 -> 0 | L44: =L43*$B$42 -> 0 | ... AM44: =AM43*$B$42 -> 0
C45: Рост цен (от стадии проекта),% | D45: =SUM(E45:T45) -> 0.32 | E45: 0.02 | F45: =E45 -> 0.02 | G45: =F45 -> 0.02 | H45: =G45 -> 0.02 | I45: =H45 -> 0.02 | J45: =I45 -> 0.02 | K45: =J45 -> 0.02 | L45: =K45 -> 0.02 | M45: =L45 -> 0.02 | ... AM45: =AL45 -> 0.02
B46: =H15 -> 600000 | C46: Цена продаж, тыс.руб./кв.м | D46: =AVERAGE(E46:S46) -> 691736.68 | E46: =B46 -> 600000 | F46: =E46+E46*E45 -> 612000 | G46: =F46+F46*F45 -> 624240 | H46: =G46+G46*G45 -> 636724.8 | I46: =H46+H46*H45 -> 649459.3 | J46: =I46+I46*I45 -> 662448.48 | K46: =J46+J46*J45 -> 675697.45 | L46: =K46+K46*K45 -> 689211.4 | M46: =L46+L46*L45 -> 702995.63 | ... AJ46: =AI46+AI46*AI45 -> 1108553.3
B47: =E16 -> 40.945 | C47: Машиноместа | D47: =SUM(E47:AU47) -> 1.3591248e+10 | E47: =E51*E49 -> 0 | F47: =F51*F49 -> 0 | G47: =G51*G49 -> 0 | H47: =H51*H49 -> 0 | I47: =I51*I49 -> 0 | J47: =J51*J49 -> 0 | K47: =K51*K49 -> 0 | L47: =L51*L49 -> 2.0318228e+08 | ... AM47: =AM51*AM49 -> 0
B48: =G16 -> 862 | C48: Темп продаж, шт | D48: =SUM(E48:AU48) -> 862 | E48: 0 | F48: 0 | G48: 0 | H48: 0 | I48: 0 | J48: 0 | K48: 0 | L48: 16 | M48: 18 | N48: 19 | O48: 21 | P48: 37 | Q48: 40 | R48: 44 | S48: 47 | T48: 56 | U48: 60 | V48: 64 | W48: 69 | X48: 78 | Y48: 45 | Z48: 30 | AA48: 41 | AB48: 34 | AC48: 36 | AD48: 38 | AE48: 39 | AF48: 19 | AG48: 11 | AH48: 0 | AI48: 0 | AJ48: 0 | AK48: 0 | AL48: 0 | AM48: 0 | AN48: 0 | AO48: 0 | AP48: 0 | AQ48: 0 | AR48: 0 | AS48: 0 | AT48: 0 | AU48: 0 | AV48: 0 | AW48: 0 | AX48: 0 | AY48: 0 | AZ48: 0 | BA48: 0 | BB48: 0 | BC48: 0
B49: =F16 -> 35294.59 | C49: Темп продаж , кв м | D49: =SUM(E49:S49) -> 9908.69 | E49: =E48*$B$47 -> 0 | F49: =F48*$B$47 -> 0 | G49: =G48*$B$47 -> 0 | H49: =H48*$B$47 -> 0 | I49: =I48*$B$47 -> 0 | J49: =J48*$B$47 -> 0 | K49: =K48*$B$47 -> 0 | L49: =L48*$B$47 -> 655.12 | ... AM49: =AM48*$B$47 -> 0
C50: Рост цен (от стадии проекта),% | D50: =SUM(E50:T50) -> 0.32 | E50: 0.02 | F50: =E50 -> 0.02 | G50: =F50 -> 0.02 | H50: =G50 -> 0.02 | I50: =H50 -> 0.02 | J50: =I50 -> 0.02 | K50: =J50 -> 0.02 | L50: =K50 -> 0.02 | M50: =L50 -> 0.02 | ... AM50: =AL50 -> 0.02
B51: =H16 -> 270000 | C51: Цена продаж, тыс.руб./шт. | D51: =AVERAGE(E51:S51) -> 311281.5 | E51: =B51 -> 270000 | F51: =E51+E51*E50 -> 275400 | G51: =F51+F51*F50 -> 280908 | H51: =G51+G51*G50 -> 286526.16 | I51: =H51+H51*H50 -> 292256.68 | J51: =I51+I51*I50 -> 298101.82 | K51: =J51+J51*J50 -> 304063.85 | L51: =K51+K51*K50 -> 310145.13 | M51: =L51+L51*L50 -> 316348.03 | ... AG51: =AF51+AF51*AF50 -> 470076.54
C52: =C17 -> Прочие помещения | D52: =SUM(E52:AU52) -> 0 | E52: =E56*E54 -> 0 | F52: =F56*F54 -> 0 | G52: =G56*G54 -> 0 | H52: =H56*H54 -> 0 | I52: =I56*I54 -> 0 | J52: =J56*J54 -> 0 | K52: =K56*K54 -> 0 | L52: =L56*L54 -> 0 | ... AM52: =AM56*AM54 -> 0
B53: =G17 -> 0 | C53: Темп продаж, шт | D53: =SUM(E53:AU53) -> 0
B54: =F17 -> 0 | C54: Темп продаж , кв м | D54: =SUM(E54:S54) -> 0
C55: Рост цен (от стадии проекта),% | D55: =SUM(E55:T55) -> 0.32 | E55: 0.02 | F55: =E55 -> 0.02 | G55: =F55 -> 0.02 | H55: =G55 -> 0.02 | I55: =H55 -> 0.02 | J55: =I55 -> 0.02 | K55: =J55 -> 0.02 | L55: =K55 -> 0.02 | M55: =L55 -> 0.02 | ... T55: =S55 -> 0.02 | U55: 2.02 | V55: 3.02 | W55: 4.02 | X55: 5.02 | Y55: 6.02 | Z55: 7.02 | AA55: 8.02 | AB55: 9.02 | AC55: 10.02 | AD55: 11.02 | AE55: 12.02 | AF55: 13.02 | AG55: 14.02 | AH55: 15.02 | AI55: 16.02 | AJ55: 17.02 | AK55: 18.02 | AL55: 19.02 | AM55: 20.02
B56: =H17 -> 0 | C56: Цена продаж, тыс.руб./шт. | D56: =AVERAGE(E56:S56) -> 0 | E56: =B56 -> 0
C58: Средняя стоимость квартир | E58: =AVERAGE(E31,E36,E41) -> 497703 | F58: =AVERAGE(F31,F36,F41) -> 507657.06 | G58: =AVERAGE(G31,G36,G41) -> 517810.2 | H58: =AVERAGE(H31,H36,H41) -> 528166.41 | I58: =AVERAGE(I31,I36,I41) -> 538729.73 | J58: =AVERAGE(J31,J36,J41) -> 549504.33 | K58: =AVERAGE(K31,K36,K41) -> 560494.41 | L58: =AVERAGE(L31,L36,L41) -> 571704.3 | ... AM58: =AVERAGE(AM31,AM36,AM41) -> 975834.34
B59: =B29+B34+B39 -> 143560.39 | C59: Темп продаж квартир | E59: =E29+E34+E39 -> 8407.416 | F59: =F29+F34+F39 -> 2614.834 | G59: =G29+G34+G39 -> 1758.958 | H59: =H29+H34+H39 -> 2169.342 | I59: =I29+I34+I39 -> 1794.066 | J59: =J29+J34+J39 -> 4561.43 | K59: =K29+K34+K39 -> 5321.668 | L59: =L29+L34+L39 -> 5980.22 | ... AO59: =AO29+AO34+AO39 -> 0
C60: Стоимость Пмоещений с НДС | D60: =SUM(E60:AO60) -> 2.3797716e+10 | E60: =E47+E52+E42 -> 0 | F60: =F47+F52+F42 -> 0 | G60: =G47+G52+G42 -> 0 | H60: =H47+H52+H42 -> 0 | I60: =I47+I52+I42 -> 0 | J60: =J47+J52+J42 -> 0 | K60: =K47+K52+K42 -> 0 | L60: =L47+L52+L42 -> 2.0318228e+08 | ... AO60: =AO47+AO52+AO42 -> 0
C61: НДС | D61: =D60*C62 -> 5.2354976e+09 | E61: =E60*$C$62 -> 0 | F61: =F60*$C$62 -> 0 | G61: =G60*$C$62 -> 0 | H61: =H60*$C$62 -> 0 | I61: =I60*$C$62 -> 0 | J61: =J60*$C$62 -> 0 | K61: =K60*$C$62 -> 0 | L61: =L60*$C$62 -> 44700101 | ... AM61: =AM60*$C$62 -> 0
C62: 0.22
C65: Средняя в конце продаж | D65: =AVERAGE(S31,S36,S41) -> 656708.54
C66: Средневзвешенная Квартир | D66: =AVERAGE(D31,D36,D41) -> 573799.03
C67: Средние темпы реализации квартир | D67: =AVERAGE(E59:S59) -> 5166.7979
D70: =SUM(E70:AV70) -> 10322.408 | E70: 0 | F70: 0 | G70: 0 | H70: 0 | I70: 0 | J70: 0 | K70: 0 | L70: 0 | M70: 0 | N70: 0 | O70: 0 | P70: 0 | Q70: 0 | R70: 0 | S70: 0 | T70: 0 | U70: 400 | V70: 400 | W70: 400 | X70: 614.2 | Y70: 891.4 | Z70: 690.3 | AA70: 1324.3 | AB70: 1094.2 | AC70: 1094.2 | AD70: 1271.2 | AE70: 762.208 | AF70: 637.2 | AG70: 177 | AH70: 177 | AI70: 177 | AJ70: 212.2 | AK70: 0 | AL70: 0 | AM70: 0 | AN70: 0 | AO70: 0 | AP70: 0 | AQ70: 0 | AR70: 0 | AS70: 0 | AT70: 0 | AU70: 0 | AV70: 0 | AW70: 0 | AX70: 0 | AY70: 0 | AZ70: 0 | BA70: 0 | BB70: 0 | BC70: 0
D71: =D70/$E$15 -> 129.0301 | E71: =E70/$E$15 -> 0 | F71: =F70/$E$15 -> 0 | G71: =G70/$E$15 -> 0 | H71: =H70/$E$15 -> 0 | I71: =I70/$E$15 -> 0 | J71: =J70/$E$15 -> 0 | K71: =K70/$E$15 -> 0 | ... AM71: =AM70/$E$15 -> 0

Sheet Эскроу
I1: ='План продаж'!#REF! -> #REF! | U1: ='План продаж'!P23 -> 0 | V1: ='План продаж'!R23 -> 0 | W1: ='План продаж'!S23 -> 0
I2: ='План продаж'!E24 -> 1 квартал 26 | J2: ='План продаж'!F24 -> 2 квартал 26 | K2: ='План продаж'!G24 -> 3 квартал 26 | L2: ='План продаж'!H24 -> 4 квартал 26 | M2: ='План продаж'!I24 -> 1 квартал 27 | N2: ='План продаж'!J24 -> 2 квартал 27 | O2: ='План продаж'!K24 -> 3 квартал 27 | P2: ='План продаж'!L24 -> 4 квартал 27 | ... AB2: ='План продаж'!X24 -> 4 квартал 30 | AC2: 1 квартал 2031 | AD2: 2 квартал 2031 | AE2: 3 квартал 2031 | AF2: 4 квартал 2031 | AG2: 1 квартал 2032 | AH2: 2 квартал 2032 | AI2: 3 квартал 2032 | AJ2: 4 квартал 2032 | AK2: 1 квартал 2033 | AL2: итого
B3: Рассрочка, кв | D3: 6 | E3: 6 | F3: 6 | G3: 6 | H3: 6 | I3: 6 | J3: 6 | K3: 6 | L3: 6 | M3: 6 | N3: 6 | O3: 6 | P3: 6 | Q3: 6 | R3: 6 | S3: 6 | T3: 6 | U3: 6 | V3: 6 | W3: 6 | AE3: 4 | AF3: 4 | AG3: 4 | AH3: 4 | AI3: 0 | AJ3: 0 | AK3: 0
B4: Сделки итого : | I4: ='План продаж'!E25 -> 4.1843962e+09 | J4: ='План продаж'!F25 -> 1.3274389e+09 | K4: ='План продаж'!G25 -> 9.108064e+08 | L4: ='План продаж'!H25 -> 1.1457736e+09 | M4: ='План продаж'!I25 -> 9.665167e+08 | N4: ='План продаж'!J25 -> 2.5065255e+09 | O4: ='План продаж'!K25 -> 2.9827652e+09 | P4: ='План продаж'!L25 -> 3.6220998e+09 | ... AK4: ='План продаж'!AG25 -> 1.0774015e+09 | AL4: =SUM(D4:AK4) -> 1.1751409e+11
B5: Сделки с рассрочкой | C5: 0 | D5: =$C$5*D4 -> 0 | E5: =$C$5*E4 -> 0 | F5: =$C$5*F4 -> 0 | G5: =$C$5*G4 -> 0 | H5: =$C$5*H4 -> 0 | I5: =$C$5*I4 -> 0 | J5: =$C$5*J4 -> 0 | K5: =$C$5*K4 -> 0 | ... AK5: =$C$5*AK4 -> 0 | AL5: =SUM(D5:AK5) -> 0
B6: Сделки с ипотекой | C6: 0.7 | D6: =$C$6*D4 -> 0 | E6: =$C$6*E4 -> 0 | F6: =$C$6*F4 -> 0 | G6: =$C$6*G4 -> 0 | H6: =$C$6*H4 -> 0 | I6: =$C$6*I4 -> 2.9290773e+09 | J6: =$C$6*J4 -> 9.2920726e+08 | K6: =$C$6*K4 -> 6.3756448e+08 | ... AK6: =$C$6*AK4 -> 7.5418103e+08 | AL6: =SUM(D6:AK6) -> 8.2259864e+10
B7: Сделки со 100% оплатой | C7: 0.1 | D7: =$C$7*D4 -> 0 | E7: =$C$7*E4 -> 0 | F7: =$C$7*F4 -> 0 | G7: =$C$7*G4 -> 0 | H7: =$C$7*H4 -> 0 | I7: =$C$7*I4 -> 4.1843962e+08 | J7: =$C$7*J4 -> 1.3274389e+08 | K7: =$C$7*K4 -> 91080640 | ... AK7: =$C$7*AK4 -> 1.0774015e+08 | AL7: =SUM(D7:AK7) -> 1.1751409e+10
B8: ПВ | C8: 0.2 | D8: 0 | E8: 0 | F8: 0 | G8: 0 | H8: 0 | I8: =I4*$C$8 -> 8.3687923e+08 | J8: =J4*$C$8 -> 2.6548779e+08 | K8: =K4*$C$8 -> 1.8216128e+08 | L8: =L4*$C$8 -> 2.2915471e+08 | M8: =M4*$C$8 -> 1.9330334e+08 | N8: =N4*$C$8 -> 5.0130511e+08 | O8: =O4*$C$8 -> 5.9655304e+08 | P8: =P4*$C$8 -> 7.2441996e+08 | ... AK8: =AK4*$C$8 -> 2.1548029e+08 | AL8: =SUM(D8:AK8) -> 2.3502818e+10
B9: Рассрочка | C9: 1 кв | AL9: =SUM(D9:AK9) -> 0
C10: 2кв | AL10: =SUM(D10:AK10) -> 0
C11: 3кв | AL11: =SUM(D11:AK11) -> 0
C12: 4кв | AL12: =SUM(D12:AK12) -> 0
C13: 5кв | AL13: =SUM(D13:AK13) -> 0
C14: 6кв | AL14: =SUM(D14:AK14) -> 0
C15: 7кв | AL15: =SUM(D15:AK15) -> 0
C16: 8кв | AL16: =SUM(D16:AK16) -> 0
C17: 9кв | AL17: =SUM(D17:AK17) -> 0
C18: 10кв | AL18: =SUM(D18:AK18) -> 0
C19: 11кв | AL19: =SUM(D19:AK19) -> 0
C20: 12кв | AL20: =SUM(D20:AK20) -> 0
C21: 13кв | AL21: =SUM(D21:AK21) -> 0
... C32: 24 кв | AL32: =SUM(D32:AK32) -> 0
B33: Итого гашение: | D33: =SUM(D6:D28) -> 0 | E33: =SUM(E6:E28) -> 0 | F33: =SUM(F6:F28) -> 0 | G33: =SUM(G6:G28) -> 0 | H33: =SUM(H6:H28) -> 0 | I33: =SUM(I6:I32) -> 4.1843962e+09 | J33: =SUM(J6:J32) -> 1.3274389e+09 | K33: =SUM(K6:K32) -> 9.108064e+08 | L33: =SUM(L6:L32) -> 1.1457736e+09 | M33: =SUM(M6:M32) -> 9.665167e+08 | N33: =SUM(N6:N32) -> 2.5065255e+09 | O33: =SUM(O6:O32) -> 2.9827652e+09 | P33: =SUM(P6:P32) -> 3.6220998e+09 | ... AL33: =SUM(AL6:AL32) -> 1.1751409e+11

Sheet Dashboard
A2: Название проекта | C2: =ТЭПы!C2 -> Дербеневская набережная по калькулятору Саевой
A3: Площадь участка | C3: =ТЭПы!C15 -> 96572
A4: Стадия ИРД
A5: Планируемый класс жилья | C5: =ТЭПы!C4 -> БИЗНЕС
A6: Дата покупки проекта | C6: =ТЭПы!C6 -> 3 кв 2025-4 кв 2025
A7: Сроки строительства | B7: =ТЭПы!C7 -> 4 кв 2025 | C7: =ТЭПы!C10 -> 30.09.2029; 01.03.2031; 01.07.2031; 01.10.2031
A9: Результаты | B9: ед.изм. | C9: Значение
A10: ТЭПы Проекта:
A11: Суммарнопоэтажная площадь - СПП | B11: кв. м | C11: =ТЭПы!C19 -> 221967
A12: Площадь в габаритах наружных стен (ГНС) | B12: кв. м
A13: Продаваемая площадь (ПП) | B13: кв. м | C13: =ТЭПы!E38 -> 189176.98
A14: Квартиры | B14: кв. м | C14: =ТЭПы!C22 -> 143560
A15: ПСН | B15: кв. м | C15: =ТЭПы!E48 -> 10322
A16: Кладовые | B16: шт. | C16: =ТЭПы!E50 -> 0
A17: Паркинг | B17: шт. | C17: =ТЭПы!F49 -> 862
A19: Выручка | B19: тыс. руб. | C19: ='CF1 '!C15 -> 1.1751409e+11
A20: Средняя цена реализации квартир
A21: на старте | B21: тыс. руб./кв. м | C21: =ТЭПы!G44 -> 497703
A22: приведенное значение к дате оценки | B22: тыс. руб./кв. м
A23: в конце продаж | B23: тыс. руб./кв. м | C23: ='План продаж'!D65 -> 656708.54
A24: средневзвешенная | B24: тыс. руб./кв. м | C24: ='План продаж'!D66 -> 573799.03
A25: Средние темпы реализацииквартир | B25: кв. м | C25: ='План продаж'!D67 -> 5166.7979
A26: Общий срок реализации всех квартир | B26: квартал | C26: =COUNTIF('План продаж'!E26:AM26,">0") -> 32
A27: Расходы | B27: тыс. руб. | C27: =SUM(C28:C32) -> 7.6888564e+10
A28: ='CF1 '!A20 -> Вход в проект | B28: тыс. руб. | C28: ='CF1 '!C20 -> 1330355898
A29: ='CF1 '!A23 -> Земельно-имущественные отношения | B29: тыс. руб./кв. м ПП | C29: ='CF1 '!C23 -> 1.9349595e+09
A30: ='CF1 '!A27 -> ПИР и ИРД | B30: тыс. руб. | C30: ='CF1 '!C27 -> 2.0131747e+09
A31: ='CF1 '!A40 -> САРЕХ | B31: тыс. руб. | C31: ='CF1 '!C40 -> 6.4742338e+10
A32: ='CF1 '!A77 -> ОРЕХ | B32: тыс. руб. | C32: ='CF1 '!C77 -> 6.8677366e+09
A33: Валовая маржа | B33: тыс. руб. | C33: =C19-C27 -> 4.0625527e+10
A34: Валовая рентабельность | B34: % | C34: =C33/C19 -> 0.34570771
A35: Налоги | B35: тыс. руб. | C35: ='CF1 '!C81 -> 6.7450962e+09
A36: Лимит финансирования | B36: тыс. руб. | C36: ='CF1 '!C98 -> -8.1180073e+10
A37: Начисленные % по кредиту | B37: тыс. руб. | C37: =-'CF1 '!C107 -> 1.4386244e+10
A38: Общий срок кредита | B38: квартал | C38: =COUNTIF('CF1 '!F98:AS98,">0") -> 0
A39: Собственное участие Акционера | B39: тыс. руб. | C39: ='CF1 '!C132 -> 8.3237147e+09
A40: Итоги по проекту | C40: =C33-(C35+C37) -> 1.9494187e+10
A41: Прибыль до финансирования | B41: тыс. руб. | C41: ='CF1 '!C138 -> 4.8267075e+10
A42: Фин рез | C42: =C19-C27-C35-C37 -> 1.9494187e+10
A43: IRR Продаж | B43: % | C43: =C40/C19 -> 0.16588808
A44: IRR Проекта | C44: =C40/(C27+C35+C37) -> 0.19887988
A45: IRR Капитала Инвестора | B45: % | C45: =C39/C41 -> 0.1724512
A46: LTV max | B46: % | C46: =MAX('CF1 '!F144:AS144) -> 0
C50: =(C27+C35+C37)/C13 -> 518138.66
C51: =('CF1 '!C138+'CF1 '!C98-'CF1 '!C107)/('CF1 '!C98-'CF1 '!C107) -> 0.27737224
A52: LLCR | C52: =('CF1 '!C138+'CF1 '!C98-'CF1 '!C107)/('CF1 '!C98-'CF1 '!C107) -> 0.27737224
A54: Расчет показателя LLCR производится или за весь период проекта или на на определенную дату.
A55: На листе рассчитан LLSR рассчитан на каждый период и выведен средний показатель
A56: Для вычисления этого показателя выводится строка NPV
A57: NPV | C57: ='CF1 '!D148 -> 4.8267075e+10
A58: LLCR средний за весь проект | C58: ='CF1 '!D150 -> 3.3550851
A61: ='CF1 '!A152 -> Альтернативный подход Банков
A62: ='CF1 '!A153 -> Выручка минус налоги | C62: ='CF1 '!D153 -> 1.2425919e+11
A63: ='CF1 '!A154 -> Общий долг (выборка + %) | C63: ='CF1 '!D154 -> 6.6793829e+10
A64: ='CF1 '!A155 -> Коэффициент покрытие долговых обязательств LLCR | C64: ='CF1 '!D155 -> 1.8603393
